{"initial":{"c":["Boundary","Boundary","DoubleJiejie","ReimuAttackW","ReimuAttackW","ReimuBlockR","ReimuBlockR","ReimuBlockR","Shoot","Shoot","Zhukeling"],"e":[]},"changes":{"1":{"add_c":["MojingShanjie"]},"2":{"add_c":["HuiyinRemove"]},"3":{"add_c":["SuikaBigball"],"rem_c":["HuiyinRemove","ReimuAttackW"]},"4":{"add_c":["HuiyinRemove"],"add_e":["TiangouRongqiu"]},"7":{"add_c":["YoumuAttack"],"rem_c":["HuiyinRemove","ReimuBlockR"]},"8":{"add_c":["HuanxiangBlock"],"add_e":["HeiseBijiben"]},"9":{"add_c":["RingoJinghua"],"add_e":["JiangyouPing"]},"10":{"add_e":["WaijieYanjing"]},"12":{"add_c":["HuiyinRemove"],"rem_c":["ReimuAttackW"]},"14":{"add_c":["YongyiAttack","YuetuInvincible"],"rem_c":["Boundary","HuiyinRemove"],"add_e":["Modaoshu"]},"16":{"add_e":["KoishiG"]},"19":{"add_c":["LunaticPassion"]},"22":{"add_e":["WaijieYouxiji"],"rem_e":["Modaoshu","WaijieYanjing"]},"23":{"add_c":["NewsTidbit"]},"24":{"add_c":["ZhujiThreeGod"]},"25":{"add_c":["ToolHeal","YuetuInvincible"]},"26":{"add_c":["DoubleDajiejie"],"add_e":["Chaidao"]},"27":{"add_e":["Shanbibu"]},"28":{"add_c":["YinglangHowl"]},"29":{"add_c":["QinggeManwu"],"rem_c":["SuikaBigball"]},"30":{"add_c":["ReimuHeavyAttack"]},"31":{"rem_c":["NewsTidbit"],"add_e":["PingfanDao"]},"33":{"add_c":["MoonWorld"],"add_e":["TianwenWangyuanjing"]},"35":{"add_c":["ZhujiThreeGod"]},"36":{"add_c":["Drunk"]},"37":{"add_c":["Regret"]},"38":{"add_c":["BoliPhantom","HuiyinRemove"],"rem_c":["Drunk"],"add_e":["Huiyuanka","LouguanJian","Shouyinji"]},"39":{"add_c":["BailianMagic"],"add_e":["WaijieYanshuang"],"rem_e":["WaijieYouxiji"]},"41":{"rem_c":["Drunk","HuiyinRemove","ToolHeal"]},"42":{"add_e":["Duandai"]},"43":{"add_e":["Shaoyao"]},"44":{"add_e":["Yashemao"]},"45":{"add_c":["XiaosanJingxia"]},"46":{"add_c":["ShengtianKick"]},"47":{"rem_c":["XiaosanJingxia"]},"48":{"add_c":["EnterEpiphany"],"add_e":["JingzhiChaju"]},"49":{"add_e":["JingjieGanzhiyi"],"rem_e":["WaijieYanshuang"]},"50":{"add_c":["ButterflyDream"],"add_e":["YueGujiu"]},"52":{"add_c":["ToolMana"]},"54":{"rem_c":["ToolMana"]}}}