{"initial":{"c":["Boundary","Boundary","CirnoAttackG","CirnoAttackG","CirnoBlockU","CirnoBlockU","CirnoBlockU","DayaojingFriend","Shoot","Shoot","Zhukeling"],"e":[]},"changes":{"0":{"add_c":["CallFriends"]},"2":{"add_c":["PlayWithWater"]},"4":{"add_c":["CirnoConsider"],"add_e":["TiangouDunpai"]},"8":{"add_c":["FruitShake"],"rem_c":["CirnoAttackG"]},"9":{"add_e":["PingfanDao"]},"10":{"add_e":["WaijieYanjing"]},"11":{"add_e":["JingesiYushou"]},"12":{"add_c":["MoreFriends"]},"14":{"add_c":["CirnoInForest"],"add_e":["JiangyouPing"]},"16":{"add_c":["YonglinDraw"],"add_e":["TaiguGouyu"]},"19":{"add_c":["CirnoInForest"]},"21":{"rem_c":["CirnoAttackG"]},"22":{"add_e":["WaijieYouxiji"],"rem_e":["PingfanDao","WaijieYanjing"]},"24":{"add_c":["HatateShot"]},"26":{"add_e":["JudaShaozi"]},"27":{"add_e":["DiyinLeigu"]},"30":{"rem_c":["Shoot"]},"31":{"add_e":["TiangouShanzi"]},"33":{"add_c":["LarvaDefense"],"add_e":["KongbaiKapai"]},"35":{"add_c":["BrainOverclock","Regret"]},"36":{"add_c":["Yuebiao"]},"38":{"add_c":["DanmuJade"]},"39":{"add_e":["WaijieYanshuang"],"rem_e":["WaijieYouxiji"]},"42":{"add_c":["FairyWrath"],"rem_c":["Yuebiao"]},"43":{"add_e":["XiaorenWan"]},"44":{"rem_c":["Shoot"],"add_e":["Bumengwang"]},"45":{"add_c":["NewsPositive"]},"46":{"add_c":["DoubleMana"]},"47":{"add_e":["JingjieGanzhiyi"],"rem_e":["WaijieYanshuang"]},"48":{"rem_c":["NewsPositive"],"add_e":["PenzaiYoutan"]},"50":{"add_c":["ZhenmiaowanAbility"],"add_e":["XianzheShi"]},"52":{"add_c":["ToolBlock"]}}}