{"initial":{"c":["Boundary","Boundary","CirnoAttackG","CirnoAttackG","CirnoBlockU","CirnoBlockU","CirnoBlockU","DayaojingFriend","Shoot","Shoot","Zhukeling"],"e":[]},"changes":{"2":{"add_c":["FairyOnIce"]},"3":{"add_c":["FruitShake"]},"4":{"rem_c":["CirnoAttackG"]},"6":{"add_c":["DayaojingFriend"]},"9":{"add_e":["ZheyangSan"]},"10":{"add_e":["WaijieYanjing"]},"12":{"add_c":["CirnoConsider"]},"13":{"add_c":["AhongMana","DayaojingFriend"],"rem_c":["CirnoAttackG"]},"14":{"add_e":["XijianSan"]},"16":{"add_c":["LimaoSchool"],"add_e":["TianwenWangyuanjing"]},"20":{"add_c":["DayaojingFriend"]},"21":{"add_c":["LarvaFriend"],"rem_c":["Shoot"]},"22":{"add_e":["WaijieYouxiji"],"rem_e":["WaijieYanjing","XijianSan"]},"23":{"add_c":["LimaoSchool"]},"25":{"add_c":["CallFriends"],"add_e":["ChuRenou"]},"26":{"add_e":["ShenmiPifeng"]},"27":{"add_e":["PortalGun"]},"31":{"add_c":["CirnoInForest"],"add_e":["YichuiPiao"]},"33":{"add_c":["YonglinDraw"],"add_e":["DatiangouMaifan"]},"36":{"add_e":["SongjingMuyu"]},"39":{"add_e":["WaijieYanshuang"],"rem_e":["WaijieYouxiji"]},"42":{"rem_c":["Shoot"]},"44":{"add_e":["Fengrenji"]},"46":{"add_c":["ShiverArmor"]},"47":{"add_c":["ToolHeal"],"rem_c":["Boundary"]},"48":{"add_c":["ChooseFriend"],"add_e":["JingzhiChaju"]},"49":{"add_e":["JingjieGanzhiyi"],"rem_e":["WaijieYanshuang"]},"50":{"add_c":["HuiyeMarblePhantasm"],"rem_c":["ToolHeal"],"add_e":["KongbaiKapai"]},"52":{"rem_c":["Boundary"]}}}