{"initial":{"c":["Astrology","Boundary","Boundary","CraftPotion","MarisaAttackB","MarisaAttackB","MarisaBlockR","MarisaBlockR","MarisaBlockR","Shoot","Shoot","Zhukeling"],"e":[]},"changes":{"0":{"rem_c":["MarisaAttackB"]},"1":{"add_c":["LeiguAttack"]},"3":{"add_c":["MeilingBlock"]},"4":{"rem_c":["MarisaAttackB"]},"10":{"add_e":["WaijieYanjing"]},"13":{"add_c":["ToolAttack"]},"14":{"add_c":["DropBook"]},"16":{"add_c":["ReisenAttack"],"rem_c":["CraftPotion"],"add_e":["SakuyaU"]},"21":{"add_c":["PlayWithWater","XiaosanReflect"]},"22":{"add_e":["WaijieYouxiji"],"rem_e":["WaijieYanjing"]},"27":{"add_e":["TiangouRongqiu"]},"28":{"add_c":["SakuyaDraw"],"add_e":["Jiaobu","ZhanshuDaoliqi"]},"29":{"add_c":["TunnelEffect"]},"30":{"rem_c":["MarisaBlockR"]},"31":{"add_c":["PlayWithWater"]},"33":{"add_c":["BrokenTimeline"],"rem_c":["LeiguAttack","ToolAttack"],"add_e":["DatiangouMaifan"]},"39":{"add_e":["WaijieYanshuang"],"rem_e":["WaijieYouxiji"]},"41":{"add_c":["NewsTidbit"]},"42":{"add_e":["JingjieGanzhiyi"],"rem_e":["WaijieYanshuang"]},"43":{"add_c":["ShengquanZaiwo"],"rem_c":["NewsTidbit"],"add_e":["Shiyou"]},"44":{"add_c":["YijiuDraw"],"add_e":["Modaoshu"]},"45":{"add_c":["LilyoftheValley"]},"46":{"add_c":["SakuyaSleep"]},"47":{"add_c":["XiaoemoBook"]},"48":{"add_c":["TunnelEffect"]},"50":{"add_c":["MasterOfCollection"],"rem_c":["LilyoftheValley"],"add_e":["YueGujiu"]},"52":{"add_c":["ToolExile"]},"54":{"rem_c":["ToolExile"]}}}