{"initial":{"c":["BaseFollower","Boundary","Boundary","KoishiAttackB","KoishiAttackB","KoishiBlockG","KoishiBlockG","KoishiBlockG","KoishiKiss","Shoot","Shoot","Zhukeling"],"e":[]},"changes":{"0":{"add_e":["FeixiangJian"]},"1":{"add_c":["RumiaBlock"]},"2":{"add_c":["CloseEye"]},"3":{"add_c":["PassionMemory"]},"4":{"add_c":["HuiyeAttack"],"add_e":["Yuhangfu"]},"6":{"add_c":["Jealousy"],"add_e":["Zuoshan"]},"7":{"add_c":["CloseEye"]},"9":{"add_e":["HuangyouJiqiren"]},"10":{"add_e":["WaijieYanjing"]},"12":{"add_c":["SunflowerDefense"]},"13":{"add_c":["YachieDefend","YuyukoDebuff"],"rem_c":["Jealousy"]},"14":{"add_e":["HuonanMianju"]},"16":{"add_c":["BlackEpiphany"],"rem_c":["BaseFollower"],"add_e":["CirnoU"]},"18":{"add_c":["LigeluCard"]},"20":{"add_c":["YukariBox"]},"21":{"add_c":["AliceAttack"]},"22":{"add_e":["WaijieYouxiji"],"rem_e":["WaijieYanjing"]},"25":{"add_c":["CallFriends"]},"26":{"add_e":["XijianSan"]},"27":{"add_e":["He3"]},"29":{"add_c":["EmpCard"]},"31":{"add_c":["HatateShot"],"add_e":["Yueshan"]},"33":{"add_c":["JinziDoppelganger"],"rem_c":["SunflowerDefense"],"add_e":["XianzheShi"]},"36":{"add_c":["KoishiDrawTop"]},"39":{"add_c":["KoishiDna"],"add_e":["WaijieYanshuang"],"rem_e":["WaijieYouxiji"]},"40":{"add_c":["LeaveMoodDraw"]},"41":{"add_c":["XiaosanJingxia"]},"42":{"add_e":["JingjieGanzhiyi"],"rem_e":["WaijieYanshuang"]},"43":{"add_e":["WanglingTideng"]},"44":{"add_e":["TiangouShouji"]},"45":{"rem_c":["XiaosanJingxia"]},"46":{"add_c":["YukariBox"]},"47":{"add_c":["EnterEpiphany"]},"48":{"add_e":["ZheyangSan"]},"50":{"add_c":["HuiyinRetain"],"rem_c":["EmpCard","Shoot","YachieDefend"],"add_e":["HouhuMen"]},"52":{"add_c":["KoishiDrawTop","MeilingWater"]},"53":{"add_c":["EnterEpiphany"]}}}