{"initial":{"c":["Boundary","Boundary","ReimuAttackR","ReimuAttackR","ReimuBlockW","ReimuBlockW","ReimuBlockW","Shoot","Shoot","YaoguaiBuster","Zhukeling"],"e":[]},"changes":{"0":{"add_e":["Yashemao"]},"1":{"add_c":["YakongDianxue"]},"2":{"add_c":["HuaBlock"]},"3":{"add_c":["LeiguAttack"]},"7":{"add_e":["JingesiYushou"]},"9":{"add_c":["QinggeManwu"],"add_e":["Jiaobu"]},"10":{"add_e":["WaijieYanjing"]},"12":{"add_c":["JingshenYishi"]},"14":{"add_c":["QinggeManwu"],"add_e":["TiangouXiangji"]},"16":{"add_c":["MomentPower"],"rem_c":["YakongDianxue"],"add_e":["CirnoU"]},"18":{"add_c":["KuosanLingfu"]},"19":{"add_c":["EvilTuiZhi"]},"21":{"rem_c":["ReimuAttackR"],"add_e":["YinzhiHuaibiao"]},"22":{"add_e":["WaijieYouxiji"],"rem_e":["Jiaobu","WaijieYanjing"]},"24":{"add_c":["EmpCard"]},"26":{"add_e":["Zixingche"]},"27":{"add_e":["DiyinLeigu"]},"30":{"add_c":["CommonFire"],"rem_c":["ReimuAttackR"]},"31":{"add_e":["Pingguo"]},"33":{"add_c":["Xiguadao"],"rem_c":["LeiguAttack"],"add_e":["PiaoliangPanzi"]},"35":{"add_c":["PlayWithWater"]},"37":{"add_c":["Wunvyu"]},"39":{"add_e":["WaijieYanshuang"],"rem_e":["WaijieYouxiji"]},"41":{"add_c":["NewsNegative"]},"42":{"add_e":["JingjieGanzhiyi"],"rem_e":["WaijieYanshuang"]},"43":{"rem_c":["ReimuBlockW"],"add_e":["Bumengwang"]},"44":{"add_e":["Heilianhua"]},"47":{"add_c":["TianziMana","ToolBlock"],"rem_c":["Boundary"]},"48":{"add_c":["YijiuDraw"],"rem_c":["EmpCard","NewsNegative"],"add_e":["ZheyangSan"]},"50":{"add_e":["GuizuJiubei"]},"52":{"add_e":["Duandai"]},"54":{"rem_c":["ToolBlock"]}}}