{"initial":{"c":["Boundary","Boundary","ReimuAttackR","ReimuAttackR","ReimuBlockW","ReimuBlockW","ReimuBlockW","Shoot","Shoot","YaoguaiBuster","Zhukeling"],"e":[]},"changes":{"0":{"add_c":["ShenziUpgradeAll"]},"1":{"add_c":["YinyangBaoyu"]},"2":{"add_c":["WolfFur"],"add_e":["WeifengHuban"]},"3":{"add_c":["QinggeManwu"]},"6":{"add_c":["YinglangHowl"]},"7":{"add_e":["IdolTshirt"]},"9":{"add_c":["TianziMana"]},"10":{"add_e":["WaijieYanjing"]},"11":{"add_c":["YoumuAttack"],"rem_c":["WolfFur"]},"12":{"rem_c":["ReimuAttackR"]},"14":{"add_c":["HuaBlock"],"add_e":["ShanshuoBishou"]},"16":{"add_c":["BlackEpiphany"],"rem_c":["YaoguaiBuster"],"add_e":["KoishiB"]},"22":{"add_e":["WaijieYouxiji"],"rem_e":["WaijieYanjing"]},"23":{"add_c":["MojingShanjie"]},"24":{"rem_c":["ReimuBlockW"]},"27":{"add_e":["ShoushiYubi"]},"28":{"add_c":["LeiguAttack"]},"29":{"add_c":["ReimuSilence"]},"31":{"add_c":["MeihongFire"],"add_e":["Mengriji"]},"33":{"add_c":["ReimuInstant"],"rem_c":["LeiguAttack"],"add_e":["DatiangouMaifan"]},"35":{"add_c":["ZhujiThreeGod"]},"39":{"add_c":["YukariSwarm"],"add_e":["WaijieYanshuang"],"rem_e":["WaijieYouxiji"]},"40":{"add_c":["LilyoftheValley"]},"42":{"add_e":["JingjieGanzhiyi"],"rem_e":["WaijieYanshuang"]},"43":{"add_e":["JiangyouPing"]},"44":{"add_e":["Zixingche"]},"45":{"add_c":["FutoLight"]},"47":{"rem_c":["ReimuAttackR"]},"48":{"rem_c":["LilyoftheValley"],"add_e":["Chaidao"]},"49":{"rem_c":["Boundary"]},"50":{"add_c":["KoishiMana"],"add_e":["HuashanBaiyaosheng"]},"52":{"add_c":["ToolAmulet","ToolDraw"],"rem_c":["Shoot"]},"53":{"rem_c":["ReimuBlockW"]},"54":{"rem_c":["ToolAmulet"]}}}