{"initial":{"c":["Boundary","Boundary","CirnoAttackG","CirnoAttackG","CirnoBlockU","CirnoBlockU","CirnoBlockU","DayaojingFriend","Shoot","Shoot","Zhukeling"],"e":[]},"changes":{"0":{"add_e":["Yashemao"]},"1":{"add_c":["IceLaser"]},"2":{"add_c":["MeilingRain"],"rem_c":["CirnoAttackG"]},"3":{"add_c":["SummerIce"]},"6":{"add_c":["CoolBreeze"]},"7":{"add_c":["CirnoInForest"]},"9":{"add_c":["YouxiangAttack"],"add_e":["Chaidao"]},"10":{"add_e":["WaijieYanjing"]},"11":{"add_c":["PlayWithWater"]},"12":{"add_c":["FreezeToIce"]},"14":{"add_c":["PlayWithWater"],"add_e":["TiangouShanzi"]},"16":{"add_c":["DanceAroundLake"],"add_e":["ReimuW"]},"18":{"add_c":["RangziFanshu"]},"20":{"add_c":["HatateDiscard"]},"22":{"add_e":["WaijieYouxiji"],"rem_e":["Chaidao","WaijieYanjing"]},"23":{"add_c":["MaidFriend"]},"26":{"add_c":["YouxiangWake"],"add_e":["ChuRenou"]},"27":{"add_e":["ShenmiPifeng"]},"28":{"add_c":["ToolAmulet","ToolBlock","ToolHeal"]},"29":{"add_c":["FreezeToIce"]},"31":{"add_c":["ChunseXiaojing"],"add_e":["Shaoyao"]},"33":{"add_c":["SkyWater"],"rem_c":["RangziFanshu"],"add_e":["GaodangShoubao","HuangyouJiqiren","HuiyeBaoxiang","Shuye"]},"35":{"add_c":["YoumuAttack"]},"37":{"add_c":["Psychedelic"],"add_e":["DiannaoPeijian"]},"38":{"add_c":["KokoroAttack"],"rem_c":["Shoot"]},"39":{"add_c":["GreenLotus"],"add_e":["WaijieYanshuang"],"rem_e":["WaijieYouxiji"]},"42":{"add_e":["JingjieGanzhiyi"],"rem_e":["WaijieYanshuang"]},"43":{"add_c":["FreezeToIce"],"add_e":["PenzaiYoutan"]},"44":{"add_c":["YijiuDraw"],"add_e":["Modaoshu","SongjingMuyu"]},"45":{"add_c":["FreezeToIce"]},"48":{"add_e":["DiyinLeigu"]},"50":{"add_c":["DoremyDuplicate"],"add_e":["YueGujiu"]},"52":{"add_c":["ReimuShrine","ToolDraw","ToolFirstAid"],"rem_c":["Shoot"]},"54":{"rem_c":["ToolAmulet"]}}}