{"initial":{"c":["Boundary","Boundary","ReimuAttackR","ReimuAttackR","ReimuBlockW","ReimuBlockW","ReimuBlockW","Shoot","Shoot","YaoguaiBuster","Zhukeling"],"e":[]},"changes":{"0":{"add_e":["Baota"]},"1":{"add_c":["PrismriverWhite"]},"2":{"add_c":["ReimuWeiyan"]},"3":{"add_c":["OverJingjie"]},"7":{"add_e":["DiannaoPeijian"],"rem_e":["DiannaoPeijian"]},"9":{"add_c":["BoliPhantom"],"add_e":["Shouyinji"]},"10":{"add_e":["WaijieYanjing"]},"12":{"add_c":["YinyangBaoyu"]},"13":{"add_c":["YinglangHowl"]},"14":{"add_c":["ReimuHeavyAttack"],"add_e":["ZheyangSan"]},"16":{"add_c":["SilverBlade"],"rem_c":["YaoguaiBuster"],"add_e":["SakuyaU"]},"19":{"add_c":["BailianNingshen"]},"22":{"add_e":["WaijieYouxiji"],"rem_e":["WaijieYanjing"]},"25":{"add_c":["RingoJinghua","ShengquanZaiwo"]},"27":{"add_c":["SilverBlade"],"add_e":["Zijing"]},"28":{"rem_c":["ReimuAttackR"]},"29":{"add_c":["MogongAttack"]},"31":{"add_e":["Fengrenji"]},"33":{"add_c":["DoubleLianhuadie"],"add_e":["GuizuJiubei"]},"36":{"add_c":["ReimuDrink"]},"37":{"add_c":["Drunk"]},"39":{"add_e":["WaijieYanshuang"],"rem_e":["WaijieYouxiji"]},"40":{"add_c":["NewsTidbit"]},"41":{"add_c":["ZhujiThreeGod"]},"42":{"rem_c":["Drunk"],"add_e":["LuoboMoxing","YinzhiHuaibiao","YueYuyi"]},"43":{"add_c":["ExileMagic"],"add_e":["TiangouMuji"]},"44":{"add_e":["LoushuiShaozi"]},"47":{"add_c":["NitoriUnderWater","ToolWeak"],"rem_c":["Drunk"],"add_e":["Pijiu"]},"48":{"add_c":["PrepareParty"],"add_e":["Pingguo"]},"49":{"add_e":["JingjieGanzhiyi"],"rem_e":["WaijieYanshuang"]},"50":{"add_e":["TianwenWangyuanjing"]}}}