{"initial":{"c":["Boundary","Boundary","CirnoAttackG","CirnoAttackG","CirnoBlockU","CirnoBlockU","CirnoBlockU","DayaojingFriend","Shoot","Shoot","Zhukeling"],"e":[]},"changes":{"1":{"add_c":["CirnoConsider"]},"2":{"add_c":["FruitShake"]},"4":{"add_c":["ToolUpgrade"],"rem_c":["CirnoAttackG"]},"6":{"add_c":["CirnoDraw"]},"7":{"add_c":["CirnoConsider"]},"8":{"add_c":["RangziFanshu","ToolAttack"],"rem_c":["CirnoAttackG"]},"9":{"add_e":["Xiangrikui"]},"10":{"add_e":["WaijieYanjing"]},"11":{"add_c":["CallFriends"]},"14":{"add_e":["TiangouYuyi"]},"16":{"add_c":["BestFriend","Blizzard","LarvaDefense"],"rem_c":["FruitShake","Shoot","ToolUpgrade"],"add_e":["ShijieSuipian"]},"19":{"add_c":["NitoriUnderWater"]},"21":{"add_c":["Tether"],"rem_c":["Boundary"]},"22":{"add_e":["WaijieYouxiji"],"rem_e":["TiangouYuyi","WaijieYanjing"]},"25":{"rem_c":["Boundary"]},"26":{"add_c":["DoubleMana"],"rem_c":["ToolAttack"],"add_e":["Tuanzi"]},"27":{"add_e":["Pingguo"]},"28":{"add_c":["MeilingRain"],"rem_c":["CirnoBlockU"]},"30":{"rem_c":["CirnoBlockU"]},"31":{"add_e":["DiyinLeigu"]},"33":{"rem_c":["Blizzard"],"add_e":["PingzhuangLinghun"]},"35":{"add_c":["RangziSeed"]},"38":{"rem_c":["CirnoBlockU"]},"39":{"add_e":["WaijieYanshuang"],"rem_e":["WaijieYouxiji"]},"42":{"add_c":["ToolMana"],"rem_c":["DayaojingFriend"]},"43":{"add_c":["BaitianCard"],"add_e":["Chaidao"]},"44":{"add_e":["LinghunBaoshi"]},"47":{"rem_c":["LarvaDefense"]},"48":{"add_e":["ZheyangSan"]},"49":{"add_e":["JingjieGanzhiyi"],"rem_e":["WaijieYanshuang"]},"50":{"rem_c":["Tether"],"add_e":["XianzheShi"]},"52":{"add_c":["ToolBlock"],"rem_c":["CallFriends"],"add_e":["Heilianhua","LuoboMoxing"]}}}