{"initial":{"c":["Boundary","Boundary","ReimuAttackR","ReimuAttackR","ReimuBlockW","ReimuBlockW","ReimuBlockW","Shoot","Shoot","YaoguaiBuster","Zhukeling"],"e":[]},"changes":{"0":{"add_e":["BaochuanMoxing"]},"1":{"add_c":["FreeFly"]},"2":{"add_c":["ZhujiThreeGod"]},"3":{"add_c":["ReverseJiejie"]},"6":{"add_c":["ZhujiThreeGod"]},"9":{"add_c":["QinggeManwu"],"add_e":["Heilianhua"]},"10":{"add_e":["WaijieYanjing"]},"11":{"add_e":["IdolTshirt"]},"12":{"add_c":["SuikaOut"]},"13":{"add_c":["DoubleDajiejie"]},"14":{"add_c":["HuaBlock"],"add_e":["Shoubiao"]},"16":{"add_c":["KuosanJiejie"],"rem_c":["YaoguaiBuster"],"add_e":["MarisaR"]},"18":{"add_c":["StarFantasy"]},"20":{"add_c":["SuikaOut"]},"22":{"add_e":["WaijieYouxiji"],"rem_e":["WaijieYanjing"]},"23":{"add_c":["MarisaEat"]},"25":{"add_c":["BulletStudy","SuperNova"],"rem_c":["ReimuAttackR"]},"26":{"add_c":["RingoJinghua"],"add_e":["JiangyouPing"]},"27":{"add_e":["Xiangrikui"]},"28":{"add_c":["YuyukoMisfortune"],"add_e":["SadinYuebing"]},"29":{"add_c":["ZhujiThreeGod"]},"31":{"add_c":["MeilingBlock"],"add_e":["Fengrenji"]},"33":{"add_c":["HuiyeMarblePhantasm"],"rem_c":["HuaBlock"],"add_e":["Ganggenier"]},"35":{"add_c":["HuojianSaoba"]},"36":{"add_c":["Psychedelic"],"add_e":["HuangyouJiqiren"]},"37":{"add_c":["FengyinYaomo"]},"38":{"add_c":["BurstDraw","StarShower","YakongDianxue"],"rem_c":["YuyukoMisfortune"]},"39":{"add_c":["ReimuSilence"],"add_e":["WaijieYanshuang"],"rem_e":["WaijieYouxiji"]},"40":{"rem_c":["Boundary"]},"41":{"add_c":["DanmuDuijue"]},"42":{"add_e":["JingjieGanzhiyi"],"rem_e":["WaijieYanshuang"]},"43":{"add_c":["StarFantasy"],"add_e":["Shaoyao"]},"44":{"add_e":["ShenmiPifeng"]},"46":{"add_c":["MeilingBlock"]},"48":{"add_c":["ReimuHeavyAttack"],"add_e":["PingfanDao"]},"49":{"add_c":["QinggeManwu"]},"50":{"add_c":["GreenLotus"],"rem_c":["Boundary","Shoot"],"add_e":["HouhuMen"]},"52":{"add_c":["BailianJingang","MomentPower","PrismriverWhite"]}}}