{"initial":{"c":["Boundary","Boundary","ReimuAttackR","ReimuAttackR","ReimuBlockW","ReimuBlockW","ReimuBlockW","Shoot","Shoot","YaoguaiBuster","Zhukeling"],"e":[]},"changes":{"1":{"add_c":["Jinfuzhen"]},"2":{"add_c":["YinyangBaoyu"]},"3":{"add_c":["WolfFur"],"add_e":["Shoubiao"]},"4":{"add_c":["BailianNingshen","YinyangXueyin"]},"7":{"add_c":["ReimuShrine"]},"9":{"add_c":["TwoBalls"],"add_e":["Mengriji"]},"10":{"add_e":["WaijieYanjing"]},"11":{"add_c":["YinyangBaoyu"]},"14":{"add_c":["FreeFly"],"add_e":["Yuhangfu"]},"16":{"add_c":["BoliPhantom"],"rem_c":["YaoguaiBuster"],"add_e":["ClassicWunvfu"]},"18":{"add_c":["YinglangHowl"]},"20":{"add_c":["JingshenYishi"]},"22":{"add_e":["WaijieYouxiji"],"rem_e":["WaijieYanjing"]},"23":{"add_c":["SmallPanding"]},"24":{"add_c":["NewsNegative"]},"26":{"rem_c":["WolfFur"],"add_e":["TiangouXiangji"]},"27":{"add_e":["BoreMianju"]},"30":{"add_c":["HuanxiangBlock","ReverseJiejie","TwoBalls","ZhujiThreeGod"],"rem_c":["Boundary"]},"31":{"add_c":["HuiyeMarblePhantasm"],"add_e":["Yaoshi"]},"33":{"add_c":["PrismriverAll"],"rem_c":["Jinfuzhen"],"add_e":["QinaKapian"]},"35":{"add_c":["ReimuWeiyan"]},"36":{"rem_c":["NewsNegative"],"add_e":["He3"]},"38":{"add_c":["RemiliaJizao"],"add_e":["JingwanMudan"]},"39":{"add_e":["WaijieYanshuang"],"rem_e":["WaijieYouxiji"]},"40":{"add_c":["Shengyan"]},"41":{"add_c":["RingoJinghua"]},"42":{"add_e":["JingjieGanzhiyi"],"rem_e":["WaijieYanshuang"]},"43":{"add_c":["FengyinYaomo"],"add_e":["TangSan"]},"44":{"add_e":["Shanbibu"]},"47":{"add_c":["ToolBlock","ToolFirstAid"],"rem_c":["Boundary"]},"48":{"add_c":["PrismriverRed"],"add_e":["ZheyangSan"]},"50":{"add_c":["Jiangshen"],"add_e":["KongbaiKapai"]},"52":{"add_c":["ReverseJiejie"],"rem_c":["Shoot"]}}}