{"initial":{"c":["Boundary","Boundary","Lijian","PrivateVision","SakuyaAttackU","SakuyaAttackU","SakuyaBlockW","SakuyaBlockW","Shoot","Shoot","Zhukeling"],"e":[]},"changes":{"1":{"add_c":["MihuanJack"]},"2":{"add_c":["YuyukoMisfortune"],"add_e":["SadinYuebing"]},"3":{"add_c":["TimeAuraAttack"]},"4":{"add_c":["SakuyaGraze","ToolBlock"],"rem_c":["YuyukoMisfortune"]},"7":{"add_c":["SakuyaGoOut"]},"9":{"add_c":["ExileMagic"]},"10":{"add_e":["WaijieYanjing"]},"11":{"add_e":["XiwangMianju"],"rem_e":["XiwangMianju"]},"13":{"add_c":["ToolFirstAid"],"rem_c":["SakuyaAttackU"]},"14":{"add_c":["SilverJump"],"add_e":["LoushuiShaozi"]},"16":{"add_c":["TimeWalk"],"rem_c":["Lijian","ToolBlock"],"add_e":["MarisaB"]},"18":{"add_c":["MarisaSteal"]},"22":{"add_e":["WaijieYouxiji"],"rem_e":["WaijieYanjing"]},"23":{"add_c":["ShengquanZaiwo"]},"24":{"add_e":["JimuWanju","ZhanshuDaoliqi"]},"26":{"add_c":["LightSpeed"],"add_e":["Xunlongchi"]},"27":{"add_e":["Yaoshi"]},"29":{"add_c":["YoumuAttack"]},"30":{"add_e":["Putao"]},"31":{"add_c":["SakuyaGoOut"],"add_e":["Mengriji"]},"33":{"add_c":["PerfectServant"],"rem_c":["TimeAuraAttack"],"add_e":["XianzheShi"]},"35":{"add_c":["SakuyaTea"]},"36":{"add_c":["SakuyaInvestigate"]},"37":{"add_c":["Drunk"]},"38":{"add_c":["ToolBlock","ToolHeal"],"rem_c":["Drunk"],"add_e":["LinghunBaoshi","YinzhiHuaibiao"]},"39":{"add_c":["TimeMagic"],"add_e":["WaijieYanshuang"],"rem_e":["WaijieYouxiji"]},"40":{"add_c":["SakuyaTea"]},"41":{"add_e":["PulpFiction"]},"42":{"rem_c":["Drunk"],"add_e":["BoliHufu"]},"44":{"add_c":["ToolHeal"],"add_e":["Zijing"]},"45":{"add_c":["FindCollection","PlayWithWater"]},"46":{"add_c":["LilyoftheValley"]},"47":{"add_e":["JingjieGanzhiyi"],"rem_e":["WaijieYanshuang"]},"48":{"add_e":["PingfanDao"]},"50":{"add_c":["SilverBlade"],"add_e":["KongbaiKapai"]},"52":{"add_c":["ToolAmulet","ToolVulnerable"]},"54":{"rem_c":["ToolAmulet","ToolHeal"]}}}