{"initial":{"c":["Boundary","Boundary","DoubleJiejie","ReimuAttackW","ReimuAttackW","ReimuBlockR","ReimuBlockR","ReimuBlockR","Shoot","Shoot","Zhukeling"],"e":[]},"changes":{"0":{"add_e":["Zuoshan"]},"1":{"add_c":["SanaeSpirit"]},"3":{"add_c":["JingshenYishi"]},"6":{"add_c":["YuyukoMisfortune"],"add_e":["SadinYuebing"]},"10":{"add_e":["WaijieYanjing"]},"13":{"rem_c":["YuyukoMisfortune"]},"16":{"add_c":["KoishiMana"],"rem_c":["DoubleJiejie"],"add_e":["KoishiG"]},"18":{"add_c":["YoumuAttack"]},"21":{"rem_c":["ReimuAttackW"]},"22":{"add_e":["WaijieYouxiji"],"rem_e":["WaijieYanjing","Zuoshan"]},"25":{"rem_c":["ReimuAttackW"]},"26":{"add_c":["ZhujiThreeGod"]},"27":{"add_e":["PortalGun"]},"30":{"add_c":["ReimuSilence","ShopDefense"],"add_e":["TiangouYuyi"]},"33":{"add_c":["KongMana"],"rem_c":["SanaeSpirit"],"add_e":["Laiwating"]},"36":{"add_c":["Regret"]},"37":{"add_c":["Drunk"]},"38":{"add_c":["QinggeManwu","ToolFirstAid","ToolMana"],"rem_c":["Drunk"]},"39":{"add_c":["KoishiPlayDiscard"],"rem_c":["KongMana"],"add_e":["WaijieYanshuang"],"rem_e":["WaijieYouxiji"]},"41":{"add_c":["RangziFanshu"]},"42":{"add_c":["KokoroFriend"],"rem_c":["Drunk"],"add_e":["Shaoyao"]},"44":{"add_e":["Taozi"]},"45":{"add_c":["XiaosanJingxia"]},"46":{"rem_c":["KoishiPlayDiscard"]},"47":{"add_c":["GreenLotus"],"rem_c":["XiaosanJingxia"]},"49":{"add_e":["JingjieGanzhiyi"],"rem_e":["WaijieYanshuang"]},"50":{"rem_c":["ToolMana"],"add_e":["TianwenWangyuanjing"]},"52":{"add_c":["ToolMana"]},"54":{"rem_c":["ToolFirstAid","ToolMana"]}}}