{"initial":{"c":["Boundary","Boundary","MarisaAttackR","MarisaAttackR","MarisaBlockB","MarisaBlockB","MarisaBlockB","RedLaser","Shoot","Shoot","Zhukeling"],"e":[]},"changes":{"1":{"add_c":["XiaoemoBook"]},"4":{"add_c":["MarisaSteal","ToolHeal"],"rem_c":["MarisaAttackR"]},"6":{"add_c":["MarisaDraw"]},"8":{"add_e":["Cookie"]},"9":{"add_c":["DropBook"]},"10":{"add_e":["WaijieYanjing"]},"12":{"rem_c":["MarisaAttackR"]},"16":{"add_c":["TannvCard"],"rem_c":["RedLaser","ToolHeal"],"add_e":["ReimuW"]},"18":{"add_c":["HuojianSaoba"]},"22":{"add_e":["WaijieYouxiji"],"rem_e":["Cookie","WaijieYanjing"]},"26":{"add_c":["QingeUpgrade"]},"27":{"add_e":["WanglingTideng"]},"30":{"add_c":["FindCollection"]},"33":{"add_c":["GrimoireStudy"],"add_e":["YueGujiu"]},"36":{"rem_c":["Shoot"],"add_e":["JingQiXi"]},"39":{"add_e":["WaijieYanshuang"],"rem_e":["WaijieYouxiji"]},"41":{"rem_c":["GrimoireStudy"]},"42":{"rem_c":["Shoot"]},"43":{"add_c":["WinterWarm"]},"47":{"rem_c":["MarisaBlockB"]},"48":{"add_c":["SuikaOut"]},"49":{"add_e":["JingjieGanzhiyi"],"rem_e":["WaijieYanshuang"]},"50":{"add_c":["PrismriverAll"],"add_e":["QinaKapian"]},"52":{"add_c":["ToolAmulet"],"rem_c":["QingeUpgrade"]},"54":{"rem_c":["ToolAmulet"]}}}