{"initial":{"c":["Boundary","Boundary","Lijian","PrivateVision","SakuyaAttackU","SakuyaAttackU","SakuyaBlockW","SakuyaBlockW","Shoot","Shoot","Zhukeling"],"e":[]},"changes":{"0":{"rem_c":["SakuyaAttackU"]},"1":{"add_c":["DefenseDraw"]},"2":{"add_c":["PlayWithWater"]},"3":{"add_c":["YuyukoMisfortune"],"add_e":["SadinYuebing"]},"4":{"rem_c":["YuyukoMisfortune"]},"7":{"add_c":["SakuyaSnow"]},"8":{"add_c":["CoolMaid"]},"9":{"add_c":["YukariFlyObject"]},"10":{"add_e":["WaijieYanjing"]},"12":{"add_c":["GainKnife"]},"14":{"add_c":["LanCard"],"add_e":["XiwangMianju"]},"16":{"add_c":["HuiyeMarblePhantasm","SakuyaShop","WaterPrincess"],"rem_c":["Lijian","Shoot"],"add_e":["ShijieSuipian"]},"18":{"add_c":["SakuyaTea"]},"19":{"add_c":["CleanRoom"]},"22":{"add_e":["WaijieYouxiji"],"rem_e":["WaijieYanjing"]},"23":{"add_c":["SilverJump"]},"24":{"add_e":["He3","JimuWanju"]},"26":{"add_c":["DangerousMagician","ShuimiUnderWater"]},"27":{"add_e":["Jiaobu"]},"28":{"add_e":["PulpFiction"]},"30":{"add_c":["ToolBlock"],"add_e":["HuliMianju"]},"31":{"add_c":["SakuyaWeak"]},"33":{"add_c":["BladePower"],"add_e":["Wanbaochui"]},"35":{"add_c":["ExileMagic","LunaDial"]},"37":{"add_c":["LunaDial","TiangouOrder"]},"39":{"add_e":["WaijieYanshuang"],"rem_e":["WaijieYouxiji"]},"40":{"rem_c":["SakuyaAttackU"]},"41":{"add_c":["MoonWorld","SakuyaInvestigate"]},"42":{"add_e":["JingjieGanzhiyi"],"rem_e":["WaijieYanshuang"]},"43":{"add_c":["SakuyaDraw"],"add_e":["Chaidao"]},"44":{"add_e":["TiangouDunpai"]},"45":{"add_c":["HuiyeMarblePhantasm"],"rem_c":["ToolBlock"]},"48":{"add_c":["RingoJinghua"],"add_e":["TiangouXiangji"]},"50":{"add_e":["YueGujiu"]},"52":{"add_e":["TiangouShouji"]}}}