{"initial":{"c":["Boundary","Boundary","KnifeBounce","SakuyaAttackW","SakuyaAttackW","SakuyaBlockU","SakuyaBlockU","SakuyaSnow","Shoot","Shoot","Zhukeling"],"e":[]},"changes":{"0":{"add_e":["KongbaiKapai"],"rem_e":["SakuyaW"]},"1":{"add_c":["UnlimitedTime"]},"2":{"add_e":["IdolTshirt"]},"3":{"add_c":["ShannvAbility"]},"6":{"add_e":["JingesiYushou"]},"7":{"add_c":["SakuyaTwiceAttack"]},"9":{"add_c":["ShengquanZaiwo"],"add_e":["DiyinLeigu"]},"10":{"add_e":["WaijieYanjing"]},"14":{"add_c":["SakuyaGraze"],"add_e":["ZhanshuDaoliqi"]},"16":{"add_c":["LanCard"],"rem_c":["KnifeBounce"],"add_e":["KoishiB"]},"18":{"add_c":["LigeluCard"]},"19":{"add_c":["DefaultPeace"]},"20":{"add_c":["SakuyaTea"]},"22":{"add_e":["WaijieYouxiji"],"rem_e":["DiyinLeigu","WaijieYanjing"]},"23":{"add_c":["YonglinUpgrade"]},"25":{"add_c":["HuiyeSuperExtraTurn","PatchouliLibrary","ToolBlock"],"rem_c":["SakuyaAttackW"]},"27":{"add_e":["ZheyangSan"]},"28":{"add_c":["LeaveMoodDraw"]},"31":{"add_c":["SakuyaFuneral"],"add_e":["Bingkuai"]},"33":{"add_c":["KoishiPotential","KokoroDance"],"rem_c":["KokoroDance","SakuyaAttackW","Shoot"],"add_e":["ShijieSuipian"]},"35":{"add_c":["TianziMana"]},"37":{"add_e":["Qingshu"]},"38":{"add_c":["SakuyaShop"],"add_e":["TiangouRongqiu"]},"39":{"add_e":["WaijieYanshuang"],"rem_e":["WaijieYouxiji"]},"40":{"add_e":["Xunlongchi"]},"41":{"add_c":["TakaneDefense"]},"42":{"add_e":["JingjieGanzhiyi"],"rem_e":["WaijieYanshuang"]},"43":{"add_c":["PeaceMemory"],"add_e":["HuangyouJiqiren"]},"44":{"add_e":["Shouyinji"]},"45":{"add_c":["HappyNewYear"]},"46":{"add_c":["ExileMagic"]},"48":{"add_c":["SeeFengshui"],"add_e":["Bianhua"]},"50":{"add_c":["ButterflyDream"],"add_e":["QinaKapian"]},"52":{"add_c":["KoishiSpringOut","SakuyaInvestigate","ToolDraw"],"add_e":["ShiyanQicai"]},"53":{"add_e":["Tuanzi"]},"54":{"rem_c":["ToolBlock"]}}}