{"initial":{"c":["Boundary","Boundary","KnifeBounce","SakuyaAttackW","SakuyaAttackW","SakuyaBlockU","SakuyaBlockU","SakuyaSnow","Shoot","Shoot","Zhukeling"],"e":[]},"changes":{"0":{"rem_c":["SakuyaAttackW"]},"2":{"add_e":["IdolTshirt"]},"3":{"add_c":["FakeTimeline"]},"6":{"add_c":["TiangouOrder"]},"9":{"add_c":["SilverBullet"],"add_e":["TiangouYuyi"]},"10":{"add_e":["WaijieYanjing"]},"14":{"add_c":["HuiyinRemove"],"rem_c":["Shoot"],"add_e":["Bumengwang"]},"16":{"add_c":["SilverBlade"],"rem_c":["HuiyinRemove","SakuyaAttackW","SilverBullet"],"add_e":["FengshouGuolan"]},"18":{"add_c":["ExileMagic"]},"19":{"add_c":["Dejavu"]},"22":{"add_e":["WaijieYouxiji"],"rem_e":["WaijieYanjing"]},"23":{"add_c":["DangerousMagician"]},"24":{"add_c":["ArtificialJewellery"]},"26":{"add_c":["HuiyinRemove"],"add_e":["BoreMianju"]},"27":{"add_e":["Shanbibu"]},"28":{"add_e":["PulpFiction"]},"29":{"add_c":["Dejavu"],"rem_c":["HuiyinRemove","Shoot"]},"31":{"add_e":["JudaShaozi"]},"33":{"add_c":["BladePower","HuiyinRemove","SpecialClock"],"rem_c":["Boundary"],"add_e":["ShijieSuipian"]},"36":{"add_c":["SakuyaGoOut"]},"37":{"add_c":["Psychedelic"],"add_e":["JimuWanju"]},"39":{"add_c":["SakuyaDio"],"add_e":["WaijieYanshuang"],"rem_e":["WaijieYouxiji"]},"40":{"add_c":["XiaosanJingxia"]},"41":{"add_c":["LilyoftheValley"]},"42":{"add_c":["SakuyaWeak","ToolHeal"],"rem_c":["XiaosanJingxia"]},"43":{"rem_c":["HuiyinRemove","SakuyaBlockU"],"add_e":["ChuRenou"]},"44":{"add_e":["TiangouShanzi"]},"45":{"add_c":["TiangouOrder"]},"47":{"add_e":["JingjieGanzhiyi"],"rem_e":["WaijieYanshuang"]},"48":{"add_c":["ShengquanZaiwo"],"add_e":["TiangouShouji"]},"50":{"add_c":["KnifeHell"],"rem_c":["LilyoftheValley","ToolHeal"],"add_e":["HuashanBaiyaosheng"]},"52":{"add_c":["YonglinUpgrade"]}}}