{"initial":{"c":["Astrology","Boundary","Boundary","CraftPotion","MarisaAttackB","MarisaAttackB","MarisaBlockR","MarisaBlockR","MarisaBlockR","Shoot","Shoot","Zhukeling"],"e":[]},"changes":{"1":{"add_c":["ShannvAbility"]},"3":{"add_c":["DarkSatellite"]},"4":{"add_c":["DropBook","ScryAttack"],"rem_c":["MarisaAttackB"]},"6":{"add_c":["MarisaEat"]},"7":{"add_c":["ReadyForBurst"]},"9":{"add_c":["SatelliteIllusion","YongyiAttack"],"add_e":["Modaoshu"]},"10":{"add_e":["WaijieYanjing"]},"11":{"rem_c":["MarisaAttackB"]},"13":{"add_c":["DropBook"],"rem_c":["Shoot"]},"14":{"add_e":["ShanshuoBishou"]},"16":{"add_c":["ChargingPotion"],"add_e":["KongbaiKapai"]},"18":{"add_c":["DropBook"]},"19":{"add_c":["WinterWarm"]},"20":{"add_c":["TianziMana"]},"22":{"add_e":["WaijieYouxiji"],"rem_e":["Modaoshu","WaijieYanjing"]},"24":{"add_c":["DropBook"]},"25":{"add_c":["ShopDefense"],"rem_c":["Shoot"]},"26":{"add_c":["BurstDraw"],"rem_c":["MarisaBlockR"],"add_e":["Bumengwang"]},"27":{"add_e":["Bianhua"]},"28":{"add_c":["ShiningPotion"]},"29":{"add_c":["PatchouliFriend"]},"30":{"add_c":["YuyukoDebuff"]},"31":{"add_e":["TiangouYuyi"]},"33":{"add_c":["SanaeMiracle"],"rem_c":["Boundary","MarisaBlockR","ShannvAbility"],"add_e":["HouhuMen"]},"35":{"add_c":["XiaoemoBook"]},"39":{"add_e":["WaijieYanshuang"],"rem_e":["WaijieYouxiji"]},"42":{"add_c":["JungleMaster"],"rem_c":["MarisaBlockR"]},"43":{"add_c":["ShiningPotion"],"add_e":["HuangyouJiqiren"]},"44":{"add_e":["Yashemao"]},"45":{"add_c":["ReadyForBurst"]},"47":{"add_c":["ShiningPotion"]},"48":{"add_c":["DanmuJade"],"add_e":["ShanliangDengpao"]},"49":{"add_e":["JingjieGanzhiyi"],"rem_e":["WaijieYanshuang"]},"50":{"add_c":["ChargingPotion"],"add_e":["ClassicWunvfu"]},"52":{"add_c":["FindCollection"]}}}