{"initial":{"c":["Boundary","Boundary","ReimuAttackR","ReimuAttackR","ReimuBlockW","ReimuBlockW","ReimuBlockW","Shoot","Shoot","YaoguaiBuster","Zhukeling"],"e":[]},"changes":{"1":{"add_c":["HuaBlock"]},"2":{"add_c":["DanmuDuijue"]},"3":{"add_c":["RingoJinghua"]},"4":{"add_c":["Zhuizongfu"],"rem_c":["ReimuAttackR"]},"6":{"add_c":["YunyouShengdi"]},"7":{"add_c":["YoumuAttack"]},"9":{"add_e":["TiangouYuyi"]},"10":{"add_e":["WaijieYanjing"]},"11":{"add_c":["ZhenmiaowanAttack"]},"14":{"add_c":["YinglangHowl"],"add_e":["Shoubiao"]},"16":{"add_c":["AyaWindGirl"],"add_e":["KoishiG"]},"18":{"add_c":["SuikaOut"]},"20":{"add_c":["MojingShanjie"]},"21":{"add_c":["QinggeManwu"],"add_e":["YinzhiHuaibiao"]},"22":{"add_e":["WaijieYouxiji"],"rem_e":["TiangouYuyi","WaijieYanjing"]},"23":{"add_c":["YinyangQueen"]},"26":{"add_c":["KoishiDrawTop"],"add_e":["XiwangMianju"]},"27":{"add_e":["SunhuaiHufu"]},"28":{"rem_c":["YinyangQueen"]},"29":{"add_c":["SanaeSummonGod"]},"31":{"add_e":["ChuRenou"]},"33":{"add_c":["ReisenAttack"],"add_e":["Bingzhilin"]},"37":{"add_e":["HuonanMianju"]},"38":{"add_c":["LilyChun"],"rem_c":["ReimuAttackR"]},"39":{"add_e":["WaijieYanshuang"],"rem_e":["WaijieYouxiji"]},"41":{"add_c":["FreeFly"]},"42":{"add_c":["RingoJinghua"]},"43":{"add_c":["RangziSeed"],"add_e":["Xiangrikui"]},"44":{"add_e":["DiyinLeigu"]},"46":{"add_c":["KoishiDrawTop"]},"47":{"add_e":["JingjieGanzhiyi"],"rem_e":["WaijieYanshuang"]},"48":{"add_e":["Mengriji"]},"50":{"add_e":["YueGujiu"]},"52":{"add_c":["HatateDiscard","ToolHeal"]}}}