{"initial":{"c":["BaseFollower","Boundary","Boundary","KoishiAttackB","KoishiAttackB","KoishiBlockG","KoishiBlockG","KoishiBlockG","KoishiKiss","Shoot","Shoot","Zhukeling"],"e":[]},"changes":{"0":{"add_e":["PiaoliangPanzi"],"rem_e":["KoishiB"]},"2":{"add_c":["KokoroFriend"]},"3":{"rem_c":["KoishiAttackB"]},"4":{"rem_c":["KoishiAttackB"]},"7":{"add_c":["SakuraBlade"],"rem_c":["Shoot"]},"9":{"add_c":["PlayDrawTop"]},"10":{"add_e":["WaijieYanjing"]},"14":{"add_c":["KoishiTouying"],"add_e":["Shoubiao"]},"16":{"add_c":["Anatta","KoishiTouying","YouxiangWake"],"rem_c":["Anatta","Boundary","Shoot"],"add_e":["ShijieSuipian"]},"18":{"add_c":["DuplicateFollower"]},"19":{"add_c":["CloseEye"]},"21":{"rem_c":["Boundary"],"add_e":["Chaidao"]},"22":{"add_e":["WaijieYouxiji"],"rem_e":["Chaidao","WaijieYanjing"]},"23":{"add_c":["KoishiKiss"]},"26":{"add_c":["KoishiDive"],"add_e":["He3"]},"27":{"add_e":["ChuRenou"]},"28":{"add_c":["NewsNegative"]},"29":{"add_c":["PlayWithWater"],"add_e":["Baota","BoreMianju"]},"30":{"add_c":["BlackEpiphany","HuiyeSuperExtraTurn","ToolBlock"]},"31":{"rem_c":["NewsNegative"],"add_e":["TiangouShanzi"]},"33":{"add_c":["SanaeRestart"],"add_e":["QicaiLianhua"]},"39":{"add_c":["HuiyeTime"],"add_e":["WaijieYanshuang"],"rem_e":["WaijieYouxiji"]},"42":{"add_e":["JingjieGanzhiyi"],"rem_e":["WaijieYanshuang"]},"43":{"add_c":["LilyChun"],"add_e":["YueYuyi"]},"44":{"add_e":["Tnt"]},"46":{"rem_c":["KoishiBlockG"]},"48":{"add_c":["KoishiDrawTop"],"add_e":["WanglingTideng"]},"50":{"add_c":["JinziDoppelganger"],"rem_c":["ToolBlock"],"add_e":["Wanbaochui"]},"52":{"add_c":["PrismriverWhite"]}}}