{"initial":{"c":["BaseFollower","Boundary","Boundary","KoishiAttackB","KoishiAttackB","KoishiBlockG","KoishiBlockG","KoishiBlockG","KoishiKiss","Shoot","Shoot","Zhukeling"],"e":[]},"changes":{"1":{"add_c":["XiaoemoBook"]},"2":{"add_e":["JingesiYushou"]},"3":{"add_c":["LigeluCard"]},"6":{"add_c":["YuyukoDebuff"]},"9":{"add_c":["KoishiDrawTop"],"add_e":["SunhuaiHufu"]},"10":{"add_e":["WaijieYanjing"]},"11":{"add_c":["YouxiangMoon"]},"12":{"add_c":["ArtificialJewellery"]},"13":{"add_c":["KoishiDrawTop","RangziFanshu","ToolAttack"],"rem_c":["KoishiAttackB"]},"14":{"add_c":["MedicineGarden"],"add_e":["Tnt"]},"16":{"add_c":["SelfControl"],"rem_c":["ToolAttack"],"add_e":["CirnoG"]},"20":{"add_c":["LarvaDefense"]},"22":{"add_e":["WaijieYouxiji"],"rem_e":["WaijieYanjing"]},"26":{"add_c":["FindInspiration"],"add_e":["BaochuanMoxing"]},"27":{"add_e":["LoushuiShaozi"]},"28":{"rem_c":["ArtificialJewellery"]},"29":{"add_c":["MarisaForget","ToolAttack","ToolExile","ToolVulnerable"]},"31":{"add_c":["PrismriverBlack"],"add_e":["Yaoshi"]},"33":{"add_c":["GainInspiration"],"rem_c":["ToolExile"],"add_e":["XianzheShi"]},"35":{"add_c":["Regret","XiaoemoBook"]},"36":{"add_c":["CloseEye"],"rem_c":["ToolAttack"]},"37":{"add_c":["Yuebiao"]},"39":{"add_c":["HuiyeAttack"],"add_e":["WaijieYanshuang"],"rem_e":["WaijieYouxiji"]},"41":{"add_c":["RangziFanshu"]},"42":{"add_e":["JingjieGanzhiyi"],"rem_e":["WaijieYanshuang"]},"43":{"add_c":["YuyukoDebuff"],"add_e":["DiannaoPeijian"]},"44":{"add_e":["ShenmiPifeng"]},"45":{"add_e":["PulpFiction"]},"46":{"add_c":["TakaneDefense"]},"48":{"add_c":["TheFool"],"add_e":["TiangouShouji"]},"50":{"add_c":["HuiyeAttack"],"rem_c":["RangziFanshu"],"add_e":["Bingzhilin"]},"52":{"add_c":["LigeluCard","ToolDraw","ToolWeak"]},"54":{"rem_c":["ToolVulnerable"]}}}