{"initial":{"c":["Astrology","Boundary","Boundary","CraftPotion","MarisaAttackB","MarisaAttackB","MarisaBlockR","MarisaBlockR","MarisaBlockR","Shoot","Shoot","Zhukeling"],"e":[]},"changes":{"1":{"add_c":["ShannvAbility"]},"2":{"add_c":["YinglangHowl"]},"4":{"add_c":["MeilingBlock","ReadyForBurst"],"rem_c":["MarisaAttackB"]},"6":{"add_e":["JingesiYushou"]},"7":{"add_e":["IdolTshirt"]},"9":{"add_c":["XiaoemoBook"],"add_e":["TiangouXiangji"]},"10":{"add_e":["WaijieYanjing"]},"11":{"add_c":["DarkSatellite"]},"13":{"add_c":["SatelliteIllusion"],"rem_c":["MarisaAttackB"]},"14":{"add_c":["WizardStudy"],"add_e":["PenzaiYoutan"]},"16":{"add_c":["OpenUniverse"],"rem_c":["CraftPotion"],"add_e":["CirnoG"]},"18":{"add_c":["BrainOverclock"]},"20":{"add_c":["ReadyForBurst"]},"21":{"add_c":["Alioth"],"rem_c":["MarisaBlockR"]},"22":{"add_e":["WaijieYouxiji"],"rem_e":["WaijieYanjing"]},"23":{"add_c":["FlanPlayAlone"],"rem_c":["MarisaBlockR"]},"26":{"add_c":["Alioth","ScryAttack"],"add_e":["Zijing"]},"27":{"add_e":["BoreMianju"]},"28":{"add_c":["Xiguadao"]},"29":{"rem_c":["MarisaBlockR"]},"31":{"add_c":["BurstDraw"],"add_e":["Tuanzi"]},"33":{"rem_c":["FlanPlayAlone"],"add_e":["TianwenWangyuanjing"]},"35":{"add_c":["MeilingBlock"],"add_e":["Qingshu"]},"37":{"add_c":["DarkSatellite"]},"39":{"add_c":["ClownpieceFriend"],"rem_c":["OpenUniverse"],"add_e":["WaijieYanshuang"],"rem_e":["WaijieYouxiji"]},"41":{"add_c":["LilyoftheValley"]},"42":{"add_c":["BrainOverclock"]},"43":{"add_c":["StarShower"],"add_e":["Bingkuai"]},"44":{"add_c":["RemiliaFate"],"add_e":["Modaoshu"]},"45":{"add_c":["RinDraw"]},"47":{"add_e":["JingjieGanzhiyi"],"rem_e":["WaijieYanshuang"]},"48":{"add_c":["DarkSatellite"],"add_e":["TiangouShanzi"]},"50":{"add_c":["SolarSystem"],"rem_c":["Shoot"],"add_e":["HouhuMen"]},"52":{"add_c":["ToolFirstAid"]}}}