{"initial":{"c":["Boundary","Boundary","CirnoAttackU","CirnoAttackU","CirnoBlockG","CirnoBlockG","CirnoBlockG","FreezeBullet","IceLance","Shoot","Shoot","Zhukeling"],"e":[]},"changes":{"0":{"add_e":["XianzheShi"],"rem_e":["CirnoU"]},"1":{"add_c":["IceLaser"]},"3":{"add_c":["DayaojingFriend"]},"6":{"add_c":["SummerIce"]},"8":{"add_c":["FairyOnIce"]},"9":{"add_c":["PlayWithWater"],"add_e":["Shoubiao"]},"10":{"add_e":["WaijieYanjing"]},"12":{"add_c":["ColdSnap"]},"14":{"add_c":["DoubleMana"],"add_e":["HuliMianju"]},"16":{"add_c":["PatchouliLibrary"],"add_e":["KongbaiKapai"]},"18":{"add_c":["CirnoDraw"]},"21":{"add_c":["ToolWeak"],"rem_c":["CirnoAttackU"],"add_e":["Huiyuanka"]},"22":{"add_e":["WaijieYouxiji"],"rem_e":["HuliMianju","WaijieYanjing"]},"23":{"add_c":["ZeroK"]},"26":{"add_c":["GlacialSpike"],"add_e":["HuanxiangxiangYuanqi"]},"27":{"add_e":["XijianSan"]},"28":{"add_c":["LunaFriend"],"rem_c":["ToolWeak"]},"29":{"add_c":["FreezeRiver"]},"30":{"add_c":["ToolDraw"],"rem_c":["CirnoAttackU"],"add_e":["LoushuiShaozi"]},"31":{"add_e":["Yaoshi"]},"33":{"rem_c":["IceLance"],"add_e":["YueGujiu"]},"35":{"add_c":["Blizzard"]},"36":{"add_c":["HatateShot"]},"37":{"add_c":["IceBarrier"]},"38":{"add_c":["ZeroK"],"add_e":["Zijing"]},"39":{"add_e":["WaijieYanshuang"],"rem_e":["WaijieYouxiji"]},"40":{"rem_c":["ToolDraw"]},"41":{"add_c":["GlacialSpike"]},"42":{"add_e":["JingjieGanzhiyi"],"rem_e":["WaijieYanshuang"]},"43":{"add_c":["DoubleMana"],"add_e":["TiangouShanzi"]},"44":{"add_e":["Yueshan"]},"45":{"add_c":["Blizzard"]},"48":{"add_e":["TiangouDunpai"]},"50":{"add_e":["HuashanBaiyaosheng"]},"52":{"add_c":["ToolMana"],"add_e":["FaliJingdian"]},"54":{"rem_c":["ToolMana"]}}}