{"initial":{"c":["Boundary","Boundary","CirnoAttackG","CirnoAttackG","CirnoBlockU","CirnoBlockU","CirnoBlockU","DayaojingFriend","Shoot","Shoot","Zhukeling"],"e":[]},"changes":{"0":{"add_e":["BaochuanMoxing"]},"1":{"add_c":["Opt"]},"2":{"add_c":["TakaneDefense"]},"3":{"add_e":["IdolTshirt"]},"6":{"add_c":["CirnoConsider"]},"7":{"add_c":["CirnoEcho"]},"9":{"add_c":["GlacialSpike"],"add_e":["PingfanDao"]},"10":{"add_e":["WaijieYanjing"]},"11":{"add_c":["MaidFriend"]},"14":{"add_e":["Bianhua"]},"16":{"add_c":["HuiyeAttack"],"add_e":["MarisaB"]},"20":{"add_c":["BaitianCard"]},"22":{"add_e":["WaijieYouxiji"],"rem_e":["IdolTshirt","WaijieYanjing"]},"23":{"add_c":["ShiningPotion"]},"24":{"add_c":["LeidiFriend"]},"26":{"add_c":["JinziDoppelganger","XiaoemoBook"],"add_e":["Modaoshu"]},"27":{"add_e":["Heilianhua"]},"28":{"add_c":["WaterPrincess"]},"30":{"add_c":["ColdPotion"],"add_e":["TiangouShanzi","Zijing"]},"31":{"add_c":["PlayWithWater"],"add_e":["Bingkuai"]},"33":{"add_c":["ExilePotion"],"rem_c":["DayaojingFriend"],"add_e":["Bingzhilin"]},"35":{"add_c":["PlayWithWater"]},"36":{"add_c":["IceBarrier"]},"39":{"add_c":["FairyTrick"],"add_e":["WaijieYanshuang"],"rem_e":["WaijieYouxiji"]},"40":{"add_c":["BlueZeroAttack"]},"41":{"rem_c":["Boundary"]},"42":{"add_e":["JingjieGanzhiyi"],"rem_e":["WaijieYanshuang"]},"43":{"add_e":["TiangouYuyi"]},"44":{"add_e":["XiwangMianju"]},"45":{"add_c":["ToolHeal","ToolVulnerable"]},"46":{"add_c":["SweetPoison"]},"47":{"add_c":["MoreFriends","ToolWeak"],"rem_c":["SweetPoison"],"add_e":["Duandai"]},"48":{"add_c":["HatateDiscard"],"add_e":["HuangyouJiqiren"]},"50":{"add_c":["GatherFairy"],"rem_c":["CirnoAttackG"],"add_e":["HouhuMen"]},"52":{"add_c":["MoguMaster","ShibaiChanwu"],"rem_c":["Boundary"]}}}