{"initial":{"c":["Boundary","Boundary","ReimuAttackR","ReimuAttackR","ReimuBlockW","ReimuBlockW","ReimuBlockW","Shoot","Shoot","YaoguaiBuster","Zhukeling"],"e":[]},"changes":{"0":{"add_c":["HuashanDefense"],"rem_c":["ReimuAttackR"]},"1":{"add_c":["YinyangBaoyu"]},"2":{"add_c":["WolfFur"],"add_e":["Saiqianxiang"]},"3":{"add_c":["ReimuWeiyan"]},"6":{"add_e":["JingesiYushou"]},"9":{"add_c":["YinglangHowl"],"rem_c":["ReimuAttackR","WolfFur"],"add_e":["Bumengwang"]},"10":{"add_e":["WaijieYanjing"]},"11":{"add_c":["YinyangXueyin"],"rem_c":["Shoot"]},"12":{"add_c":["QinggeManwu"]},"13":{"add_c":["LingfuHuti","YakongDianxue"],"rem_c":["ReimuBlockW"]},"14":{"add_c":["JingshenYishi"],"add_e":["Tnt"]},"16":{"add_c":["HuanxiangTouying"],"rem_c":["YaoguaiBuster"],"add_e":["KoishiB"]},"18":{"add_c":["DanmuDuijue"]},"21":{"add_c":["GapLady"],"rem_c":["ReimuBlockW"]},"22":{"add_e":["WaijieYouxiji"],"rem_e":["Tnt","WaijieYanjing"]},"24":{"add_c":["YuyukoDebuff"]},"26":{"add_e":["Chaidao"]},"27":{"add_e":["Fengrenji"]},"30":{"add_c":["MeilingBlock"],"rem_c":["ReimuBlockW"]},"31":{"add_c":["MengzhiYuzha"],"add_e":["JingzhiChaju"]},"33":{"add_c":["KoishiTouying"],"rem_c":["HuashanDefense"],"add_e":["KongbaiKapai"]},"35":{"add_c":["QinggeManwu"]},"36":{"add_c":["KoishiDive"]},"38":{"add_c":["DanmuDuijue","SijiCard"],"rem_c":["Boundary"]},"39":{"add_e":["WaijieYanshuang"],"rem_e":["WaijieYouxiji"]},"40":{"add_e":["HeiseBijiben"]},"41":{"add_c":["SuikaOut"]},"42":{"add_e":["JingjieGanzhiyi"],"rem_e":["WaijieYanshuang"]},"43":{"add_c":["YinyangQueen"],"add_e":["XijianSan"]},"44":{"add_e":["Heilianhua"]},"47":{"add_c":["ToolMana"],"rem_c":["Shoot"]},"48":{"add_e":["Shaoyao"]},"50":{"rem_c":["Boundary","MengzhiYuzha"],"add_e":["HouhuMen"]},"52":{"add_c":["YinyangQueen"]},"54":{"rem_c":["ToolMana"]}}}