{"initial":{"c":["Boundary","Boundary","CirnoAttackU","CirnoAttackU","CirnoBlockG","CirnoBlockG","CirnoBlockG","FreezeBullet","IceLance","Shoot","Shoot","Zhukeling"],"e":[]},"changes":{"0":{"rem_c":["CirnoAttackU"]},"1":{"add_c":["CallFriends"]},"2":{"add_c":["MeilingRain"],"rem_c":["CirnoAttackU"]},"3":{"add_c":["LongArm"]},"7":{"add_c":["QingeDraw"]},"9":{"add_e":["JingzhiChaju"]},"10":{"add_e":["WaijieYanjing"]},"14":{"add_c":["PlayWithWater"],"add_e":["Putao"]},"16":{"add_c":["Xiguadao"],"rem_c":["IceLance"],"add_e":["ReimuR"]},"18":{"add_c":["TodayYesterday"]},"19":{"add_c":["BailianPower"]},"22":{"add_e":["WaijieYouxiji"],"rem_e":["Putao","WaijieYanjing"]},"23":{"add_c":["Opt"]},"26":{"add_e":["Bingkuai"]},"27":{"add_e":["Yuhangfu"]},"28":{"add_c":["EmpCard"]},"30":{"add_c":["CirnoFire","ToolBlock"],"rem_c":["Shoot"],"add_e":["Duandai"]},"31":{"add_c":["BrainOverclock"],"add_e":["TangSan"]},"33":{"add_c":["KuosanJiejie"],"rem_c":["LongArm"],"add_e":["DatiangouMaifan"]},"35":{"add_c":["CirnoConsider"]},"37":{"add_c":["Yuebiao"]},"38":{"add_c":["DanmuJade"],"add_e":["DiannaoPeijian"]},"39":{"add_c":["SanaeRice"],"rem_c":["KuosanJiejie"],"add_e":["WaijieYanshuang"],"rem_e":["WaijieYouxiji"]},"40":{"add_c":["LilyoftheValley"]},"41":{"add_c":["MinengZhuru"],"rem_c":["ToolBlock"]},"42":{"rem_c":["Shoot"],"add_e":["HeijiaoChangpian"]},"43":{"add_c":["DanmuDuijue"],"add_e":["Tuanzi"]},"44":{"add_e":["HuangyouJiqiren"]},"45":{"add_c":["Zhulianshen"]},"47":{"add_e":["JingjieGanzhiyi"],"rem_e":["WaijieYanshuang"]},"48":{"add_c":["Changzhizhen"],"add_e":["Heilianhua"]},"50":{"add_c":["YouxiangWake"],"rem_c":["Boundary","EmpCard","LilyoftheValley"],"add_e":["HouhuMen"]},"52":{"rem_c":["CirnoBlockG"]},"53":{"add_c":["QiqingYishi"]}}}