{"initial":{"c":["Boundary","Boundary","CirnoAttackU","CirnoAttackU","CirnoBlockG","CirnoBlockG","CirnoBlockG","FreezeBullet","IceLance","Shoot","Shoot","Zhukeling"],"e":[]},"changes":{"1":{"add_c":["DayaojingFriend"]},"2":{"add_c":["WolfFur"],"add_e":["ShenmiPifeng"]},"3":{"add_c":["ColdChain"]},"4":{"add_c":["ToolWeak"],"rem_c":["CirnoAttackU"]},"6":{"add_c":["GlacialSpike"]},"7":{"add_c":["Blizzard"],"rem_c":["WolfFur"]},"9":{"add_e":["TiangouMuji"]},"10":{"add_e":["WaijieYanjing"]},"13":{"add_c":["PlayWithWater"],"rem_c":["CirnoAttackU"]},"14":{"add_e":["PortalGun"]},"16":{"add_c":["IceMatrix"],"rem_c":["DayaojingFriend"],"add_e":["TaiguGouyu"]},"18":{"add_c":["ZeroK"]},"19":{"add_c":["CirnoConsider"]},"22":{"add_e":["WaijieYouxiji"],"rem_e":["TiangouMuji","WaijieYanjing"]},"24":{"add_c":["FreezeToIce"]},"26":{"add_c":["IceBarrier"],"add_e":["TiangouShanzi"]},"27":{"add_e":["Shanbibu"]},"28":{"add_e":["IdolTshirt"]},"29":{"add_c":["Blizzard"]},"30":{"add_c":["FairyOnIce"],"rem_c":["Shoot"]},"31":{"add_e":["PingfanDao"]},"33":{"rem_c":["IceLance","ToolWeak"],"add_e":["YueGujiu"]},"36":{"add_c":["GlacialSpike"]},"38":{"add_c":["ToolBlock","ToolMana"],"add_e":["HeijiaoChangpian"]},"39":{"add_c":["YonglinCard"],"rem_c":["ColdChain"],"add_e":["WaijieYanshuang"],"rem_e":["WaijieYouxiji"]},"40":{"add_c":["MoonSea"]},"42":{"add_e":["JingjieGanzhiyi"],"rem_e":["WaijieYanshuang"]},"43":{"add_e":["WeifengHuban"]},"44":{"add_e":["Xunlongchi"]},"46":{"add_c":["ZeroK"]},"47":{"add_e":["Bingkuai"]},"48":{"add_c":["LifeGame"],"add_e":["Modaoshu"]},"49":{"add_e":["Jiaobu"]},"50":{"add_c":["FairyTeam","GatherFairy"],"rem_c":["CirnoBlockG","Shoot"],"add_e":["ShijieSuipian"]},"52":{"add_c":["ToolDroneBlock","ZeroK"]},"53":{"add_e":["Pingguo"]},"54":{"rem_c":["ToolBlock","ToolDroneBlock","ToolMana"]}}}