{"initial":{"c":["Boundary","Boundary","KnifeBounce","SakuyaAttackW","SakuyaAttackW","SakuyaBlockU","SakuyaBlockU","SakuyaSnow","Shoot","Shoot","Zhukeling"],"e":[]},"changes":{"0":{"add_c":["ExileMagic"],"rem_c":["SakuyaAttackW"]},"1":{"add_c":["SakuyaSleep"]},"2":{"add_c":["CoolMaid"]},"3":{"rem_c":["SakuyaAttackW"]},"4":{"add_c":["ShuimuBlock"],"add_e":["TiangouYuyi"]},"9":{"add_c":["YukariSwarm"],"add_e":["HuonanMianju"]},"10":{"add_e":["WaijieYanjing"]},"11":{"add_e":["Mengriji"],"rem_e":["HuonanMianju"]},"12":{"add_c":["Dejavu"]},"14":{"add_e":["Shaoyao"]},"16":{"add_c":["SakuyaDio"],"rem_c":["KnifeBounce","Shoot"],"add_e":["HouhuMen"]},"20":{"add_c":["MeilingFriend"]},"21":{"add_e":["Jiaobu"]},"22":{"add_e":["WaijieYouxiji"],"rem_e":["WaijieYanjing"]},"25":{"add_c":["HatateDiscard","KnifeDamageUp"]},"26":{"add_c":["YonglinDraw"],"add_e":["XiwangMianju"]},"27":{"add_c":["GreenLotus"],"add_e":["Modaoshu"]},"28":{"add_c":["YuyukoMisfortune"],"add_e":["SadinYuebing"]},"30":{"rem_c":["YuyukoMisfortune"]},"31":{"add_c":["PlayWithWater"],"add_e":["TiangouXiangji"]},"33":{"add_c":["UnlimitedTime"],"add_e":["ClassicWunvfu"]},"36":{"add_c":["SilverJump"]},"37":{"add_c":["Psychedelic"],"add_e":["BoreMianju"]},"39":{"add_c":["SilverBlade"],"add_e":["WaijieYanshuang"],"rem_e":["WaijieYouxiji"]},"41":{"add_c":["UnlimitedTime"]},"42":{"add_e":["JingjieGanzhiyi"],"rem_e":["WaijieYanshuang"]},"43":{"add_c":["KnifeDamageUp"],"add_e":["Pingguo"]},"44":{"add_e":["LoushuiShaozi"]},"45":{"add_c":["NewsNegative"]},"46":{"add_c":["CleanRoom"]},"48":{"rem_c":["NewsNegative"],"add_e":["HuliMianju"]},"50":{"add_c":["BladePower"],"add_e":["TaiguGouyu"]},"52":{"add_c":["RangziSeed"],"rem_c":["Boundary"],"add_e":["FaliJingdian"]}}}