{"initial":{"c":["Boundary","Boundary","MarisaAttackR","MarisaAttackR","MarisaBlockB","MarisaBlockB","MarisaBlockB","RedLaser","Shoot","Shoot","Zhukeling"],"e":[]},"changes":{"1":{"add_c":["AsteroidBelt"]},"2":{"add_c":["StarShower"]},"8":{"add_c":["ToolAttack","WinterWarm"]},"9":{"add_c":["Alioth"],"add_e":["HuliMianju"]},"10":{"add_e":["WaijieYanjing"]},"12":{"add_e":["Dianshiji"]},"14":{"add_e":["Yashemao"]},"16":{"add_c":["RemiliaBat"],"add_e":["YizangnuoWuzhi"]},"18":{"add_c":["PrismriverRed"]},"21":{"add_c":["SolarSystem"],"rem_c":["ToolAttack"],"add_e":["ShanliangDengpao","TiangouMuji"]},"22":{"add_e":["WaijieYouxiji"],"rem_e":["ShanliangDengpao","WaijieYanjing"]},"23":{"add_c":["YinglangHowl"]},"25":{"add_e":["FaliJingdian"]},"26":{"add_e":["HuanxiangxiangYuanqi","ZhanshuDaoliqi"]},"27":{"add_e":["BoreMianju"]},"28":{"add_e":["FirstAidBook"],"rem_e":["HuanxiangxiangYuanqi"]},"31":{"add_c":["StarFantasy"],"add_e":["JingzhiChaju","TangSan"]},"33":{"add_c":["GrimoireStudy","MarisaHoldCard","StarlightTaifengSummoner"],"rem_c":["MarisaAttackR","Shoot","StarFantasy"],"add_e":["ShijieSuipian"]},"35":{"add_c":["PlayWithWater"]},"38":{"add_c":["YuyukoDebuff"],"add_e":["Bianhua","GanzhuYao"]},"39":{"add_e":["WaijieYanshuang"],"rem_e":["WaijieYouxiji"]},"40":{"add_c":["BurstDraw"]},"42":{"add_e":["Duandai"]},"43":{"add_e":["HuonanMianju","Xiangrikui"]},"44":{"add_e":["Shanbibu"]},"46":{"add_c":["LilyoftheValley"]},"47":{"add_c":["ToolHeal"],"rem_c":["MarisaBlockB"]},"48":{"add_c":["Alioth","YongyiAttack"],"add_e":["Modaoshu","ShenmiPifeng"]},"49":{"add_e":["JingjieGanzhiyi"],"rem_e":["WaijieYanshuang"]},"50":{"add_c":["HuoliQuankai"],"rem_c":["MarisaBlockB","Shoot"],"add_e":["HouhuMen"]},"52":{"add_c":["ToolAttack"],"rem_c":["MarisaAttackR"]}}}