{"initial":{"c":["Boundary","Boundary","Lijian","PrivateVision","SakuyaAttackU","SakuyaAttackU","SakuyaBlockW","SakuyaBlockW","Shoot","Shoot","Zhukeling"],"e":[]},"changes":{"1":{"add_c":["NazrinBaota"]},"2":{"add_c":["YoumuAttack"]},"6":{"add_c":["SakuyaGoOut"]},"7":{"add_c":["DropToKnife"],"rem_c":["SakuyaAttackU"]},"9":{"add_c":["TimeLord"],"add_e":["WanglingTideng"]},"10":{"add_e":["WaijieYanjing"]},"12":{"add_c":["AttackMagic"]},"13":{"add_c":["DangerousMagician","ToolDraw"]},"14":{"add_c":["SanaeSpirit"],"add_e":["Tuanzi"]},"16":{"add_c":["SakuyaShop"],"rem_c":["Lijian"],"add_e":["KoishiG"]},"18":{"add_c":["SakuyaSpeedup"]},"20":{"add_c":["ShengquanZaiwo"]},"22":{"add_e":["WaijieYouxiji"],"rem_e":["WaijieYanjing"]},"23":{"add_c":["LunaDial"],"rem_c":["ToolDraw"]},"24":{"add_e":["IdolTshirt"]},"26":{"add_c":["FakeTimeline"],"add_e":["TiangouShanzi"]},"27":{"add_e":["Saiqianxiang"]},"28":{"rem_c":["TimeLord"]},"30":{"add_c":["DefaultPeace","ReadBook","ToolWeak"],"rem_c":["Shoot"]},"31":{"add_c":["KoishiDive"],"add_e":["XijianSan"]},"33":{"add_c":["ShuimuBlock","SpecialClock","StopTime"],"rem_c":["AttackMagic","SakuyaAttackU","Shoot"],"add_e":["ShijieSuipian"]},"37":{"add_c":["SakuyaGoOut"]},"39":{"add_c":["ButterflyDream"],"add_e":["WaijieYanshuang"],"rem_e":["WaijieYouxiji"]},"41":{"add_c":["QingeDraw"]},"42":{"add_e":["ShiyanQicai","Shuye"]},"43":{"add_c":["TimeWalk"],"add_e":["ChuRenou"]},"44":{"add_e":["Xiangrikui"]},"45":{"add_c":["LilyoftheValley"]},"46":{"add_c":["CleanRoom"]},"47":{"add_e":["JingjieGanzhiyi"],"rem_e":["WaijieYanshuang"]},"48":{"add_e":["ShanshuoBishou"]},"50":{"add_c":["SilverBlade"],"add_e":["TianwenWangyuanjing"]},"52":{"add_c":["ToolVulnerable","ToolWeak"],"add_e":["BoliHufu"]},"54":{"rem_c":["LilyoftheValley","ToolWeak"]}}}