{"initial":{"c":["Boundary","Boundary","DoubleJiejie","ReimuAttackW","ReimuAttackW","ReimuBlockR","ReimuBlockR","ReimuBlockR","Shoot","Shoot","Zhukeling"],"e":[]},"changes":{"0":{"add_e":["ZhangchibangQiu"]},"1":{"add_c":["HuaBlock"]},"3":{"add_c":["GainTreasure"]},"4":{"add_c":["ChuanyueJiejie","ZhujiThreeGod"]},"6":{"add_c":["Jinfuzhen"]},"7":{"add_c":["YinyangBaoyu"]},"8":{"add_c":["LingfuHuti"]},"9":{"add_c":["MojingShanjie"],"add_e":["PingfanDao"]},"10":{"add_e":["WaijieYanjing"]},"11":{"add_c":["YunyouShengdi"]},"12":{"add_c":["DoubleDajiejie"]},"13":{"add_e":["Shanbibu"]},"14":{"add_e":["WeifengHuban"]},"16":{"add_c":["ChuanyueJiejie"],"rem_c":["DoubleJiejie"],"add_e":["YueGujiu"]},"21":{"add_c":["ShopAttack"],"rem_c":["ReimuBlockR"],"add_e":["TiangouYuyi","Yushenqian"]},"22":{"add_e":["WaijieYouxiji"],"rem_e":["WaijieYanjing"]},"23":{"rem_c":["HuaBlock"]},"24":{"add_c":["ReimuShrine"]},"25":{"rem_c":["ReimuBlockR"],"add_e":["ShiyanQicai"]},"26":{"add_e":["Fengrenji"]},"27":{"add_e":["ZheyangSan"]},"28":{"add_c":["YakongDianxue"]},"29":{"add_c":["LingfuHuti"]},"30":{"rem_c":["ReimuBlockR"],"add_e":["XijianSan"]},"31":{"add_c":["YukariSwarm"],"add_e":["Modaoshu"]},"33":{"add_c":["BoliPhantom","HappyNewYear","HuijuQiankun"],"rem_c":["Boundary","HappyNewYear"],"add_e":["ShijieSuipian"]},"38":{"add_c":["KuosanLingfu"],"add_e":["JimuWanju"]},"39":{"add_c":["PatchouliLibrary"],"add_e":["WaijieYanshuang"],"rem_e":["WaijieYouxiji"]},"40":{"add_c":["Yuebiao"]},"41":{"add_c":["TwoBalls"]},"42":{"add_c":["PatchouliLibrary"],"rem_c":["ReimuAttackW","Yuebiao"],"add_e":["Bumengwang"]},"43":{"add_e":["GaodangShoubao"]},"44":{"add_e":["Heilianhua","LoushuiShaozi"]},"45":{"add_c":["ZhujiThreeGod"]},"47":{"add_c":["HuanxiangBlock"],"add_e":["Huiyuanka","Shouyinji"]},"48":{"add_e":["Pingguo"]},"49":{"add_e":["JingjieGanzhiyi"],"rem_e":["WaijieYanshuang"]},"50":{"add_c":["BoliDajiejie"],"rem_c":["ReimuAttackW","Shoot"],"add_e":["HouhuMen"]},"52":{"rem_c":["Shoot"],"add_e":["ShenmiPifeng","TangSan"]}}}