{"initial":{"c":["Boundary","Boundary","CirnoAttackG","CirnoAttackG","CirnoBlockU","CirnoBlockU","CirnoBlockU","DayaojingFriend","Shoot","Shoot","Zhukeling"],"e":[]},"changes":{"1":{"add_c":["FairyWrath"]},"2":{"add_c":["RangziSeed"]},"6":{"rem_c":["CirnoAttackG"]},"9":{"add_c":["FairyOnIce"]},"10":{"add_e":["WaijieYanjing"]},"11":{"add_c":["YuyukoMisfortune"],"add_e":["SadinYuebing"]},"12":{"add_c":["TakaneDefense"]},"13":{"add_c":["LarvaFriend","RangziFanshu"],"rem_c":["YuyukoMisfortune"]},"14":{"add_c":["DanmuJade"]},"16":{"add_c":["MinengZhuru"],"add_e":["TianwenWangyuanjing"]},"20":{"add_c":["ColdChain"]},"22":{"add_e":["WaijieYouxiji"],"rem_e":["WaijieYanjing"]},"23":{"add_c":["IceBarrier"]},"25":{"add_c":["ToolHeal"],"rem_c":["Shoot"]},"26":{"add_c":["DoubleMana"],"add_e":["Shuye"]},"27":{"add_e":["Xiangrikui"]},"28":{"add_c":["NewsNegative"]},"29":{"add_c":["CallFriends"]},"31":{"add_c":["CirnoConsider"],"add_e":["Shoubiao"]},"33":{"add_c":["InstantFreeze"],"rem_c":["IceBarrier","NewsNegative"],"add_e":["DatiangouMaifan"]},"36":{"add_c":["CirnoDraw"]},"37":{"add_c":["MoonPurify"]},"38":{"rem_c":["CirnoAttackG"],"add_e":["Headphone"]},"39":{"add_e":["WaijieYanshuang"],"rem_e":["WaijieYouxiji"]},"40":{"add_c":["LilyoftheValley"]},"42":{"add_e":["JingjieGanzhiyi"],"rem_e":["WaijieYanshuang"]},"43":{"add_e":["ShenmiPifeng"]},"44":{"add_e":["Yaoshi"]},"46":{"add_c":["RingoJinghua"]},"48":{"add_c":["PlayWithWater"],"add_e":["JingzhiChaju"]},"50":{"add_c":["HualiIce"],"add_e":["QinaKapian"]},"52":{"add_c":["ToolFirstAid"]},"54":{"rem_c":["LilyoftheValley","ToolHeal"]}}}