{"initial":{"c":["Boundary","Boundary","CirnoAttackU","CirnoAttackU","CirnoBlockG","CirnoBlockG","CirnoBlockG","FreezeBullet","IceLance","Shoot","Shoot","Zhukeling"],"e":[]},"changes":{"1":{"add_c":["LeidiFriend"]},"2":{"add_c":["ColdBreath"],"rem_c":["CirnoAttackU"]},"4":{"add_c":["Opt"],"add_e":["Yashemao"]},"6":{"add_c":["YuyukoMisfortune"],"add_e":["SadinYuebing"]},"7":{"add_c":["CirnoInForest"]},"8":{"add_c":["LeidiFriend","ShiverArmor"],"rem_c":["YuyukoMisfortune"]},"9":{"add_c":["DoubleMana"]},"10":{"add_e":["WaijieYanjing"]},"12":{"add_c":["FreezeToIce"]},"13":{"add_c":["FreezeToIce"],"rem_c":["CirnoAttackU"]},"14":{"add_c":["LeidiFriend"]},"16":{"add_c":["GatherFairy","InstantFreeze","YuyukoSing"],"rem_c":["CirnoBlockG","IceLance","Shoot"],"add_e":["ShijieSuipian"]},"19":{"rem_c":["YuyukoSing"]},"20":{"add_c":["Blizzard"]},"22":{"add_e":["WaijieYouxiji"],"rem_e":["WaijieYanjing"]},"23":{"rem_c":["LeidiFriend"]},"26":{"add_c":["CirnoConsider"]},"27":{"add_e":["Shoubiao"]},"29":{"add_c":["CirnoConsider"]},"31":{"add_c":["TakaneDefense"],"add_e":["WanglingTideng"]},"33":{"add_c":["ColdChain"],"rem_c":["ShiverArmor"],"add_e":["HuashanBaiyaosheng"]},"35":{"add_c":["ColdSnap"]},"36":{"add_c":["NitoriUnderWater"]},"37":{"add_c":["MoonPurify"]},"38":{"add_e":["ZhinengYinxiang"]},"39":{"add_e":["WaijieYanshuang"],"rem_e":["WaijieYouxiji"]},"40":{"add_c":["HualiIce"]},"42":{"add_e":["JingjieGanzhiyi"],"rem_e":["WaijieYanshuang"]},"43":{"add_e":["Yaoshi"]},"44":{"add_e":["ZhangchibangQiu"]},"45":{"add_c":["XiaosanJingxia"]},"46":{"add_c":["PlayWithWater"]},"47":{"add_c":["HatateDiscard","IceBarrier","ToolMicai"],"rem_c":["XiaosanJingxia"]},"48":{"add_e":["TiangouMuji"]},"50":{"add_c":["HuiyeAttack"],"add_e":["TianwenWangyuanjing"]},"52":{"add_c":["FreezeToIce"]}}}