{"initial":{"c":["Boundary","Boundary","CirnoAttackU","CirnoAttackU","CirnoBlockG","CirnoBlockG","CirnoBlockG","FreezeBullet","IceLance","Shoot","Shoot","Zhukeling"],"e":[]},"changes":{"0":{"add_c":["SunflowerDefense"],"rem_c":["CirnoAttackU"]},"1":{"add_c":["NitoriUnderWater"]},"3":{"add_e":["JingesiYushou"]},"6":{"add_c":["DanmuJade"]},"7":{"rem_c":["CirnoAttackU"]},"8":{"rem_c":["Shoot"]},"9":{"add_e":["JimuWanju"]},"10":{"add_e":["WaijieYanjing"]},"12":{"add_c":["LarvaFriend"]},"14":{"add_e":["Tnt"]},"16":{"add_c":["DanceAroundLake"],"rem_c":["SunflowerDefense"],"add_e":["ReimuR"]},"18":{"add_c":["JingyeGraze"]},"20":{"add_c":["GlacialSpike"]},"22":{"add_e":["WaijieYouxiji"],"rem_e":["JimuWanju","WaijieYanjing"]},"23":{"add_c":["PlayWithWater"]},"24":{"add_c":["IceBlock"]},"25":{"add_c":["ColdBreath","PlayWithWater"],"rem_c":["Shoot"],"add_e":["BoliHufu"]},"26":{"add_c":["Blizzard"],"add_e":["TiangouShanzi"]},"27":{"add_e":["BaochuanMoxing"]},"28":{"add_c":["YuyukoMisfortune"],"add_e":["SadinYuebing"]},"30":{"rem_c":["YuyukoMisfortune"]},"31":{"add_c":["FreezeToIce"],"add_e":["TiangouYuyi"]},"33":{"add_c":["SkyWater"],"rem_c":["IceLance"],"add_e":["TaiguGouyu"]},"36":{"add_c":["FreezeToIce"],"add_e":["Zijing"]},"38":{"add_e":["BoreMianju"]},"39":{"add_c":["YonglinCard"],"add_e":["WaijieYanshuang"],"rem_e":["WaijieYouxiji"]},"42":{"add_c":["DoubleMana","ToolDraw"],"rem_c":["CirnoBlockG"]},"43":{"add_c":["ZeroK"],"add_e":["PingfanDao"]},"44":{"add_e":["PenzaiYoutan"]},"45":{"add_c":["LilyoftheValley"]},"47":{"add_e":["HeijiaoChangpian"]},"48":{"add_e":["TiangouRongqiu"]},"49":{"add_e":["JingjieGanzhiyi"],"rem_e":["WaijieYanshuang"]},"50":{"add_c":["YonglinDraw"],"rem_c":["CirnoBlockG"],"add_e":["HouhuMen"]},"52":{"rem_c":["Boundary"]}}}