{"initial":{"c":["Boundary","Boundary","CirnoAttackG","CirnoAttackG","CirnoBlockU","CirnoBlockU","CirnoBlockU","DayaojingFriend","Shoot","Shoot","Zhukeling"],"e":[]},"changes":{"1":{"add_c":["YouxiangMoon"]},"2":{"add_c":["LarvaFriend"]},"3":{"add_c":["RangziSeed"]},"6":{"add_c":["WolfFur"],"add_e":["ZheyangSan"]},"7":{"add_c":["CirnoConsider"]},"9":{"add_c":["CirnoConsider"]},"10":{"add_e":["WaijieYanjing"]},"12":{"add_c":["FairyOnIce"],"rem_c":["WolfFur"]},"13":{"add_c":["DanmuJade"],"rem_c":["CirnoAttackG"]},"14":{"add_e":["PingfanDao"]},"16":{"add_c":["HuiyeAttack"],"rem_c":["DayaojingFriend"],"add_e":["MarisaR"]},"18":{"add_c":["BrainOverclock"]},"22":{"add_e":["WaijieYouxiji"],"rem_e":["PingfanDao","WaijieYanjing"]},"23":{"add_c":["YuyukoMisfortune"],"add_e":["SadinYuebing"]},"25":{"add_c":["MeilingAbility","ToolHeal"],"rem_c":["YuyukoMisfortune"],"add_e":["Huiyuanka"]},"26":{"add_e":["Saiqianxiang"]},"27":{"add_e":["Pingguo"]},"28":{"add_c":["YonglinCard"]},"31":{"add_e":["DiannaoPeijian"]},"33":{"add_c":["InstantFreeze"],"rem_c":["CirnoAttackG","CirnoBlockU","YouxiangMoon"],"add_e":["HouhuMen"]},"36":{"add_c":["BulletStudy"],"rem_c":["ToolHeal"]},"38":{"rem_c":["CirnoBlockU"],"add_e":["LuoboMoxing"]},"39":{"add_e":["WaijieYanshuang"],"rem_e":["WaijieYouxiji"]},"40":{"add_c":["NewsTidbit"]},"42":{"add_e":["JingjieGanzhiyi"],"rem_e":["WaijieYanshuang"]},"43":{"rem_c":["NewsTidbit"]},"44":{"add_c":["AyaExtraTurn"],"add_e":["Modaoshu"]},"46":{"add_e":["FirstAidBook"],"rem_e":["Modaoshu"]},"47":{"add_c":["ToolAmulet"],"rem_c":["Shoot"],"add_e":["BoliHufu","Headphone"]},"48":{"add_c":["CirnoConsider"],"add_e":["JingzhiChaju"]},"50":{"add_e":["QinaKapian"]},"52":{"add_e":["ShiyanQicai"]},"54":{"rem_c":["ToolAmulet"]}}}