{"initial":{"c":["Boundary","Boundary","DefaultPassion","DefaultPeace","KoishiAttackG","KoishiAttackG","KoishiBlockB","KoishiBlockB","Shoot","Shoot","Zhukeling"],"e":[]},"changes":{"1":{"add_c":["KoishiWake"]},"2":{"add_c":["KoishiFlower"]},"3":{"add_c":["WolfFur"],"add_e":["JiangyouPing"]},"6":{"add_c":["DanmuJade"]},"7":{"add_c":["AncestorDream"],"rem_c":["KoishiAttackG"]},"9":{"add_c":["DuplicateFollower"],"add_e":["SunhuaiHufu"]},"10":{"add_e":["WaijieYanjing"]},"12":{"add_c":["KoishiFire"],"rem_c":["WolfFur"]},"13":{"add_c":["TheHermit","ToolBlock","ToolHeal"]},"14":{"add_c":["MedicineGarden"],"add_e":["Shouyinji"]},"16":{"add_c":["GainInspiration"],"rem_c":["MedicineGarden"],"add_e":["DatiangouMaifan"]},"18":{"add_c":["KokoroDance"],"rem_c":["ToolBlock"]},"19":{"add_c":["KoishiDrawTop"]},"22":{"add_e":["WaijieYouxiji"],"rem_e":["WaijieYanjing"]},"23":{"add_c":["KoishiDrawTop"]},"24":{"add_c":["Misfortune"]},"26":{"add_c":["MoodChangeBlock"],"rem_c":["ToolHeal"],"add_e":["ShenmiPifeng"]},"27":{"add_e":["Yaoshi"]},"28":{"add_c":["MarisaForget","ToolAmulet","ToolAttack","ToolBlock"]},"29":{"add_c":["DreamExpress"]},"31":{"add_c":["KoishiFire"],"rem_c":["ToolBlock"],"add_e":["Shiyou"]},"33":{"add_c":["ButterflyDream","KoishiPotential","PeaceMemory"],"rem_c":["KoishiBlockB","KoishiFire","Shoot"],"add_e":["ShijieSuipian"]},"35":{"add_c":["Regret"]},"36":{"add_c":["GrazeFollowAttack"]},"37":{"add_c":["Psychedelic"],"add_e":["XijianSan"]},"38":{"add_c":["ToolHeal","YunyouShengdi","Zhulianshen"],"rem_c":["Shoot"],"add_e":["ShoubiaoMazuiqiang"]},"39":{"add_e":["WaijieYanshuang"],"rem_e":["WaijieYouxiji"]},"40":{"add_c":["NewsTidbit"]},"41":{"add_c":["LeaveMoodGraze"],"rem_c":["ToolAmulet"]},"42":{"add_e":["JingjieGanzhiyi"],"rem_e":["WaijieYanshuang"]},"43":{"add_e":["Shanbibu"]},"44":{"add_e":["Shoubiao"]},"45":{"add_c":["PeaceEndTurn"]},"46":{"rem_c":["DreamExpress"]},"48":{"add_c":["NitoriUnderWater"],"add_e":["GanzhuYao"]},"50":{"add_c":["ButterflyDream"],"rem_c":["NewsTidbit","ToolAttack","ToolHeal"],"add_e":["ClassicWunvfu"]},"52":{"add_c":["SunflowerDefense","ToolMana"],"rem_c":["Boundary"]},"54":{"rem_c":["ToolMana"]}}}