{"initial":{"c":["Boundary","Boundary","KnifeBounce","SakuyaAttackW","SakuyaAttackW","SakuyaBlockU","SakuyaBlockU","SakuyaSnow","Shoot","Shoot","Zhukeling"],"e":[]},"changes":{"0":{"add_c":["YonglinDraw"]},"1":{"add_c":["ReadBook"]},"2":{"add_c":["NitoriUnderWater"]},"3":{"add_c":["DropToKnife"]},"6":{"add_c":["SakuyaWeak"]},"7":{"add_c":["DangerousMagician"]},"9":{"add_c":["HuiyinRemove"],"add_e":["ShenmiPifeng"]},"10":{"add_e":["WaijieYanjing"]},"11":{"add_c":["Jealousy"],"add_e":["Heilianhua"]},"12":{"add_c":["SanaeSpirit"],"rem_c":["HuiyinRemove","SakuyaAttackW"]},"13":{"add_c":["SakuyaClock","ToolBlock"],"rem_c":["SakuyaAttackW"]},"14":{"add_c":["FakeTimeline"],"add_e":["ChuRenou"]},"16":{"add_c":["HatateDiscard","TimeMagic","YonglinCard"],"rem_c":["KnifeBounce","SakuyaBlockU","Shoot"],"add_e":["ShijieSuipian"]},"18":{"add_c":["RingoJinghua"]},"19":{"add_c":["SakuyaGoOut"]},"20":{"add_c":["ShuimuBlock"]},"22":{"add_e":["WaijieYouxiji"],"rem_e":["WaijieYanjing"]},"23":{"add_c":["SakuyaDefenseRetain"]},"24":{"add_c":["SakuyaDefenseRetain"]},"25":{"add_c":["DefenseDraw","WaterPrincess"]},"26":{"add_c":["ReadBook"],"add_e":["HuliMianju"]},"27":{"add_e":["Bianhua"]},"29":{"add_c":["ShengquanZaiwo"]},"31":{"add_c":["TimeWalk"],"add_e":["TiangouShanzi"]},"33":{"add_c":["SakuyaDio"],"rem_c":["SakuyaClock"],"add_e":["Bingzhilin"]},"35":{"add_c":["PrismriverWhite"]},"37":{"add_e":["TiangouDunpai"]},"39":{"add_c":["LunaClock"],"add_e":["WaijieYanshuang"],"rem_e":["WaijieYouxiji"]},"41":{"add_c":["PrepareParty"]},"42":{"add_e":["JingjieGanzhiyi"],"rem_e":["WaijieYanshuang"]},"43":{"add_c":["LunaClock","WaterPrincess"],"add_e":["Zijing"]},"48":{"add_e":["Pingguo"]},"50":{"add_c":["SakuyaShop"],"rem_c":["ToolBlock"],"add_e":["XianzheShi"]},"52":{"add_c":["ShopAttack","ToolWeak"]}}}