{"initial":{"c":["Boundary","Boundary","ReimuAttackR","ReimuAttackR","ReimuBlockW","ReimuBlockW","ReimuBlockW","Shoot","Shoot","YaoguaiBuster","Zhukeling"],"e":[]},"changes":{"0":{"add_c":["YinyangXueyin"],"rem_c":["ReimuAttackR"]},"1":{"add_c":["DanmuDuijue"]},"2":{"add_c":["MeihongAttack"]},"3":{"add_c":["WolfFur"],"add_e":["Pingguo"]},"6":{"add_c":["RemiliaBat"]},"7":{"add_c":["ReverseJiejie"]},"9":{"add_c":["ReimuShrine"],"rem_c":["WolfFur"],"add_e":["ShoushiYubi"]},"10":{"add_e":["WaijieYanjing"]},"11":{"add_e":["ShenmiPifeng"],"rem_e":["Pingguo"]},"12":{"add_c":["FengyinYaomo"]},"13":{"rem_c":["ReimuBlockW"]},"14":{"add_c":["QinggeManwu"],"add_e":["TiangouDunpai"]},"16":{"add_c":["KuosanJiejie"],"rem_c":["YaoguaiBuster"],"add_e":["ClassicWunvfu"]},"18":{"add_c":["JiejieAttack"]},"20":{"add_c":["FengjiAttack"]},"22":{"add_e":["WaijieYouxiji"],"rem_e":["WaijieYanjing"]},"23":{"add_e":["Xiyiji"]},"24":{"add_c":["SuikaOut"]},"25":{"rem_c":["ReimuAttackR"]},"26":{"add_c":["MoonSea"],"add_e":["TiangouYuyi"]},"27":{"add_e":["He3"]},"28":{"add_c":["DoubleDajiejie"],"add_e":["BaochuanMoxing","TiangouMuji"]},"29":{"add_c":["EmpCard"]},"30":{"rem_c":["Shoot"]},"31":{"add_c":["DanmuDuijue"],"add_e":["LinghunBaoshi"]},"32":{"rem_c":["Shoot"]},"33":{"add_c":["ReimuGrace","ToolFirstAid"],"rem_c":["MeihongAttack"],"add_e":["Gongjuxiang"]},"36":{"add_c":["PrismriverWhite","ToolWeak"]},"37":{"add_c":["LingfuHuti"]},"38":{"rem_c":["ReimuBlockW"]},"39":{"add_c":["ReimuGrace"],"add_e":["WaijieYanshuang"],"rem_e":["WaijieYouxiji"]},"40":{"add_c":["DanmuDuijue","ToolAmulet"]},"41":{"add_c":["MoonSea"],"rem_c":["ToolAmulet"]},"42":{"rem_c":["ReimuBlockW"],"add_e":["JingjieGanzhiyi"],"rem_e":["WaijieYanshuang"]},"43":{"add_c":["QinggeManwu","ToolMicai"],"add_e":["Zuoshan"]},"44":{"add_e":["ChaojiMogu"]},"45":{"add_c":["MoonPurify"]},"46":{"add_c":["ToolFirstAid"],"add_e":["FixBook"]},"47":{"rem_c":["YinyangXueyin"]},"48":{"add_c":["ZhujiThreeGod"],"add_e":["HuangyouJiqiren"]},"49":{"rem_c":["Boundary"]},"50":{"add_c":["ToolVulnerable"],"rem_c":["Boundary","KuosanJiejie","ToolWeak"],"add_e":["HouhuMen"]},"52":{"add_c":["ToolBlock","ToolMana"],"add_e":["Chaidao","FaliJingdian"]}}}